[
  {
    "date": "2023-06-22",
    "individual_predictions": {
      "cf_glm_model": 0.471,
      "cf_lda_model": 0.896,
      "cf_nn_model": 0.554,
      "cf_nn_nn_model": 0.251,
      "cf_rf_model": 0.678,
      "cf_svm_model": 0.522,
      "cg_glm_model": 0.448,
      "cg_lda_model": 1.0,
      "cg_nn_model": 0.417,
      "cg_rf_model": 0.423,
      "cg_svm_model": 0.102
    },
    "ensemble": {
      "cf": 0.5619323995228674,
      "cg": 0.47797272369245103,
      "overall": 0.5238181818181818
    },
    "features": {
      "latitude": 23.25,
      "longitude": 119.25
    }
  },
  {
    "date": "2023-06-22",
    "individual_predictions": {
      "cf_glm_model": 0.467,
      "cf_lda_model": 0.89,
      "cf_nn_model": 0.554,
      "cf_nn_nn_model": 0.251,
      "cf_rf_model": 0.664,
      "cf_svm_model": 0.5,
      "cg_glm_model": 0.498,
      "cg_lda_model": 1.0,
      "cg_nn_model": 0.556,
      "cg_rf_model": 0.405,
      "cg_svm_model": 0.089
    },
    "ensemble": {
      "cf": 0.5542638401205898,
      "cg": 0.5095995916345137,
      "overall": 0.534
    },
    "features": {
      "latitude": 23.25,
      "longitude": 119.5
    }
  },
  {
    "date": "2023-06-22",
    "individual_predictions": {
      "cf_glm_model": 0.47,
      "cf_lda_model": 0.898,
      "cf_nn_model": 0.554,
      "cf_nn_nn_model": 0.251,
      "cf_rf_model": 0.683,
      "cf_svm_model": 0.517,
      "cg_glm_model": 0.459,
      "cg_lda_model": 1.0,
      "cg_nn_model": 0.556,
      "cg_rf_model": 0.408,
      "cg_svm_model": 0.099
    },
    "ensemble": {
      "cf": 0.5621935826592273,
      "cg": 0.5045843183498583,
      "overall": 0.535909090909091
    },
    "features": {
      "latitude": 23.5,
      "longitude": 119.5
    }
  },
  {
    "date": "2023-06-22",
    "individual_predictions": {
      "cf_glm_model": 0.473,
      "cf_lda_model": 0.906,
      "cf_nn_model": 0.554,
      "cf_nn_nn_model": 0.251,
      "cf_rf_model": 0.667,
      "cf_svm_model": 0.528,
      "cg_glm_model": 0.43,
      "cg_lda_model": 1.0,
      "cg_nn_model": 0.417,
      "cg_rf_model": 0.403,
      "cg_svm_model": 0.107
    },
    "ensemble": {
      "cf": 0.5632925867031776,
      "cg": 0.47141988291886144,
      "overall": 0.5214545454545454
    },
    "features": {
      "latitude": 23.75,
      "longitude": 119.5
    }
  },
  {
    "date": "2023-06-22",
    "individual_predictions": {
      "cf_glm_model": 0.465,
      "cf_lda_model": 0.882,
      "cf_nn_model": 0.554,
      "cf_nn_nn_model": 0.251,
      "cf_rf_model": 0.653,
      "cf_svm_model": 0.5,
      "cg_glm_model": 0.52,
      "cg_lda_model": 1.0,
      "cg_nn_model": 0.729,
      "cg_rf_model": 0.39,
      "cg_svm_model": 0.083
    },
    "ensemble": {
      "cf": 0.5509318538853791,
      "cg": 0.5443175261895541,
      "overall": 0.5479090909090909
    },
    "features": {
      "latitude": 23.25,
      "longitude": 119.75
    }
  },
  {
    "date": "2023-06-22",
    "individual_predictions": {
      "cf_glm_model": 0.468,
      "cf_lda_model": 0.887,
      "cf_nn_model": 0.554,
      "cf_nn_nn_model": 0.251,
      "cf_rf_model": 0.688,
      "cf_svm_model": 0.508,
      "cg_glm_model": 0.484,
      "cg_lda_model": 1.0,
      "cg_nn_model": 0.556,
      "cg_rf_model": 0.375,
      "cg_svm_model": 0.092
    },
    "ensemble": {
      "cf": 0.5595875260440641,
      "cg": 0.5014518119074541,
      "overall": 0.5329999999999999
    },
    "features": {
      "latitude": 23.5,
      "longitude": 119.75
    }
  },
  {
    "date": "2023-06-22",
    "individual_predictions": {
      "cf_glm_model": 0.47,
      "cf_lda_model": 0.906,
      "cf_nn_model": 0.554,
      "cf_nn_nn_model": 0.251,
      "cf_rf_model": 0.7,
      "cf_svm_model": 0.511,
      "cg_glm_model": 0.474,
      "cg_lda_model": 1.0,
      "cg_nn_model": 0.556,
      "cg_rf_model": 0.388,
      "cg_svm_model": 0.095
    },
    "ensemble": {
      "cf": 0.5653167214511498,
      "cg": 0.5026712102679118,
      "overall": 0.5368181818181817
    },
    "features": {
      "latitude": 23.75,
      "longitude": 119.75
    }
  },
  {
    "date": "2023-06-22",
    "individual_predictions": {
      "cf_glm_model": 0.467,
      "cf_lda_model": 0.857,
      "cf_nn_model": 0.554,
      "cf_nn_nn_model": 0.251,
      "cf_rf_model": 0.671,
      "cf_svm_model": 0.51,
      "cg_glm_model": 0.481,
      "cg_lda_model": 0.667,
      "cg_nn_model": 0.556,
      "cg_rf_model": 0.38,
      "cg_svm_model": 0.093
    },
    "ensemble": {
      "cf": 0.5517087801527044,
      "cg": 0.435549648749802,
      "overall": 0.4988181818181818
    },
    "features": {
      "latitude": 22.75,
      "longitude": 120.0
    }
  },
  {
    "date": "2023-06-22",
    "individual_predictions": {
      "cf_glm_model": 0.463,
      "cf_lda_model": 0.794,
      "cf_nn_model": 0.554,
      "cf_nn_nn_model": 0.251,
      "cf_rf_model": 0.587,
      "cf_svm_model": 0.488,
      "cg_glm_model": 0.538,
      "cg_lda_model": 0.709,
      "cg_nn_model": 0.729,
      "cg_rf_model": 0.37,
      "cg_svm_model": 0.079
    },
    "ensemble": {
      "cf": 0.5227463460276539,
      "cg": 0.4850096441129887,
      "overall": 0.5056363636363637
    },
    "features": {
      "latitude": 23.0,
      "longitude": 120.0
    }
  },
  {
    "date": "2023-06-22",
    "individual_predictions": {
      "cf_glm_model": 0.463,
      "cf_lda_model": 0.792,
      "cf_nn_model": 0.554,
      "cf_nn_nn_model": 0.251,
      "cf_rf_model": 0.581,
      "cf_svm_model": 0.488,
      "cg_glm_model": 0.537,
      "cg_lda_model": 0.676,
      "cg_nn_model": 0.729,
      "cg_rf_model": 0.3,
      "cg_svm_model": 0.079
    },
    "ensemble": {
      "cf": 0.521523257722236,
      "cg": 0.4641399808924903,
      "overall": 0.4954545454545455
    },
    "features": {
      "latitude": 23.25,
      "longitude": 120.0
    }
  },
  {
    "date": "2023-06-22",
    "individual_predictions": {
      "cf_glm_model": 0.464,
      "cf_lda_model": 0.804,
      "cf_nn_model": 0.554,
      "cf_nn_nn_model": 0.251,
      "cf_rf_model": 0.576,
      "cf_svm_model": 0.488,
      "cg_glm_model": 0.537,
      "cg_lda_model": 0.656,
      "cg_nn_model": 0.729,
      "cg_rf_model": 0.3,
      "cg_svm_model": 0.079
    },
    "ensemble": {
      "cf": 0.5227513091604751,
      "cg": 0.4600886060818272,
      "overall": 0.49436363636363634
    },
    "features": {
      "latitude": 23.5,
      "longitude": 120.0
    }
  },
  {
    "date": "2023-06-22",
    "individual_predictions": {
      "cf_glm_model": 0.464,
      "cf_lda_model": 0.817,
      "cf_nn_model": 0.554,
      "cf_nn_nn_model": 0.251,
      "cf_rf_model": 0.561,
      "cf_svm_model": 0.488,
      "cg_glm_model": 0.537,
      "cg_lda_model": 0.636,
      "cg_nn_model": 0.729,
      "cg_rf_model": 0.3,
      "cg_svm_model": 0.079
    },
    "ensemble": {
      "cf": 0.5223633495419242,
      "cg": 0.45611808946896265,
      "overall": 0.49236363636363634
    },
    "features": {
      "latitude": 23.75,
      "longitude": 120.0
    }
  },
  {
    "date": "2023-06-22",
    "individual_predictions": {
      "cf_glm_model": 0.466,
      "cf_lda_model": 0.826,
      "cf_nn_model": 0.554,
      "cf_nn_nn_model": 0.251,
      "cf_rf_model": 0.463,
      "cf_svm_model": 0.492,
      "cg_glm_model": 0.524,
      "cg_lda_model": 0.959,
      "cg_nn_model": 0.729,
      "cg_rf_model": 0.365,
      "cg_svm_model": 0.082
    },
    "ensemble": {
      "cf": 0.5085240537370591,
      "cg": 0.5316386646218156,
      "overall": 0.5191818181818182
    },
    "features": {
      "latitude": 24.0,
      "longitude": 120.0
    }
  },
  {
    "date": "2023-06-22",
    "individual_predictions": {
      "cf_glm_model": 0.465,
      "cf_lda_model": 0.831,
      "cf_nn_model": 0.554,
      "cf_nn_nn_model": 0.251,
      "cf_rf_model": 0.68,
      "cf_svm_model": 0.507,
      "cg_glm_model": 0.494,
      "cg_lda_model": 0.793,
      "cg_nn_model": 0.556,
      "cg_rf_model": 0.355,
      "cg_svm_model": 0.09
    },
    "ensemble": {
      "cf": 0.5480239267628256,
      "cg": 0.45775216933187063,
      "overall": 0.506909090909091
    },
    "features": {
      "latitude": 22.25,
      "longitude": 120.25
    }
  },
  {
    "date": "2023-06-22",
    "individual_predictions": {
      "cf_glm_model": 0.467,
      "cf_lda_model": 0.774,
      "cf_nn_model": 0.554,
      "cf_nn_nn_model": 0.251,
      "cf_rf_model": 0.725,
      "cf_svm_model": 0.511,
      "cg_glm_model": 0.482,
      "cg_lda_model": 0.566,
      "cg_nn_model": 0.556,
      "cg_rf_model": 0.233,
      "cg_svm_model": 0.093
    },
    "ensemble": {
      "cf": 0.5468988942553322,
      "cg": 0.38612937782896195,
      "overall": 0.4738181818181818
    },
    "features": {
      "latitude": 22.5,
      "longitude": 120.25
    }
  },
  {
    "date": "2023-06-22",
    "individual_predictions": {
      "cf_glm_model": 0.467,
      "cf_lda_model": 0.786,
      "cf_nn_model": 0.554,
      "cf_nn_nn_model": 0.251,
      "cf_rf_model": 0.677,
      "cf_svm_model": 0.51,
      "cg_glm_model": 0.482,
      "cg_lda_model": 0.575,
      "cg_nn_model": 0.556,
      "cg_rf_model": 0.15,
      "cg_svm_model": 0.093
    },
    "ensemble": {
      "cf": 0.5409057842445119,
      "cg": 0.37114377076869975,
      "overall": 0.4637272727272727
    },
    "features": {
      "latitude": 22.75,
      "longitude": 120.25
    }
  },
  {
    "date": "2023-06-22",
    "individual_predictions": {
      "cf_glm_model": 0.466,
      "cf_lda_model": 0.746,
      "cf_nn_model": 0.554,
      "cf_nn_nn_model": 0.251,
      "cf_rf_model": 0.681,
      "cf_svm_model": 0.5,
      "cg_glm_model": 0.505,
      "cg_lda_model": 0.606,
      "cg_nn_model": 0.729,
      "cg_rf_model": 0.113,
      "cg_svm_model": 0.087
    },
    "ensemble": {
      "cf": 0.5328953411592118,
      "cg": 0.40810457421257834,
      "overall": 0.47618181818181815
    },
    "features": {
      "latitude": 23.0,
      "longitude": 120.25
    }
  },
  {
    "date": "2023-06-22",
    "individual_predictions": {
      "cf_glm_model": 0.463,
      "cf_lda_model": 0.753,
      "cf_nn_model": 0.554,
      "cf_nn_nn_model": 0.251,
      "cf_rf_model": 0.63,
      "cf_svm_model": 0.488,
      "cg_glm_model": 0.538,
      "cg_lda_model": 0.519,
      "cg_nn_model": 0.729,
      "cg_rf_model": 0.133,
      "cg_svm_model": 0.079
    },
    "ensemble": {
      "cf": 0.5231657461581448,
      "cg": 0.3996380550603846,
      "overall": 0.46699999999999997
    },
    "features": {
      "latitude": 23.25,
      "longitude": 120.25
    }
  },
  {
    "date": "2023-06-22",
    "individual_predictions": {
      "cf_glm_model": 0.464,
      "cf_lda_model": 0.75,
      "cf_nn_model": 0.554,
      "cf_nn_nn_model": 0.251,
      "cf_rf_model": 0.626,
      "cf_svm_model": 0.488,
      "cg_glm_model": 0.538,
      "cg_lda_model": 0.59,
      "cg_nn_model": 0.729,
      "cg_rf_model": 0.125,
      "cg_svm_model": 0.079
    },
    "ensemble": {
      "cf": 0.5220491536551437,
      "cg": 0.41210286073342123,
      "overall": 0.4721818181818182
    },
    "features": {
      "latitude": 23.5,
      "longitude": 120.25
    }
  },
  {
    "date": "2023-06-22",
    "individual_predictions": {
      "cf_glm_model": 0.465,
      "cf_lda_model": 0.788,
      "cf_nn_model": 0.554,
      "cf_nn_nn_model": 0.251,
      "cf_rf_model": 0.555,
      "cf_svm_model": 0.492,
      "cg_glm_model": 0.525,
      "cg_lda_model": 0.96,
      "cg_nn_model": 0.729,
      "cg_rf_model": 0.16,
      "cg_svm_model": 0.082
    },
    "ensemble": {
      "cf": 0.5176276499271933,
      "cg": 0.49104158239561213,
      "overall": 0.5055454545454545
    },
    "features": {
      "latitude": 23.75,
      "longitude": 120.25
    }
  },
  {
    "date": "2023-06-22",
    "individual_predictions": {
      "cf_glm_model": 0.466,
      "cf_lda_model": 0.792,
      "cf_nn_model": 0.554,
      "cf_nn_nn_model": 0.251,
      "cf_rf_model": 0.564,
      "cf_svm_model": 0.492,
      "cg_glm_model": 0.525,
      "cg_lda_model": 0.926,
      "cg_nn_model": 0.729,
      "cg_rf_model": 0.215,
      "cg_svm_model": 0.082
    },
    "ensemble": {
      "cf": 0.5197757879191656,
      "cg": 0.4952357792030189,
      "overall": 0.5087272727272727
    },
    "features": {
      "latitude": 24.0,
      "longitude": 120.25
    }
  },
  {
    "date": "2023-06-22",
    "individual_predictions": {
      "cf_glm_model": 0.469,
      "cf_lda_model": 0.862,
      "cf_nn_model": 0.554,
      "cf_nn_nn_model": 0.251,
      "cf_rf_model": 0.469,
      "cf_svm_model": 0.5,
      "cg_glm_model": 0.491,
      "cg_lda_model": 0.853,
      "cg_nn_model": 0.556,
      "cg_rf_model": 0.205,
      "cg_svm_model": 0.09
    },
    "ensemble": {
      "cf": 0.5175313505403646,
      "cg": 0.4389984436128139,
      "overall": 0.4818181818181818
    },
    "features": {
      "latitude": 24.25,
      "longitude": 120.25
    }
  },
  {
    "date": "2023-06-22",
    "individual_predictions": {
      "cf_glm_model": 0.462,
      "cf_lda_model": 0.908,
      "cf_nn_model": 0.554,
      "cf_nn_nn_model": 0.251,
      "cf_rf_model": 0.61,
      "cf_svm_model": 0.494,
      "cg_glm_model": 0.53,
      "cg_lda_model": 0.947,
      "cg_nn_model": 0.729,
      "cg_rf_model": 0.3,
      "cg_svm_model": 0.082
    },
    "ensemble": {
      "cf": 0.5464291725427781,
      "cg": 0.5174286595740527,
      "overall": 0.5333636363636364
    },
    "features": {
      "latitude": 21.75,
      "longitude": 120.5
    }
  },
  {
    "date": "2023-06-22",
    "individual_predictions": {
      "cf_glm_model": 0.463,
      "cf_lda_model": 0.876,
      "cf_nn_model": 0.554,
      "cf_nn_nn_model": 0.251,
      "cf_rf_model": 0.656,
      "cf_svm_model": 0.5,
      "cg_glm_model": 0.514,
      "cg_lda_model": 0.892,
      "cg_nn_model": 0.729,
      "cg_rf_model": 0.315,
      "cg_svm_model": 0.085
    },
    "ensemble": {
      "cf": 0.5499955910091184,
      "cg": 0.5070789951566492,
      "overall": 0.5304545454545455
    },
    "features": {
      "latitude": 22.0,
      "longitude": 120.5
    }
  },
  {
    "date": "2023-06-22",
    "individual_predictions": {
      "cf_glm_model": 0.465,
      "cf_lda_model": 0.821,
      "cf_nn_model": 0.554,
      "cf_nn_nn_model": 0.251,
      "cf_rf_model": 0.636,
      "cf_svm_model": 0.506,
      "cg_glm_model": 0.494,
      "cg_lda_model": 0.772,
      "cg_nn_model": 0.556,
      "cg_rf_model": 0.365,
      "cg_svm_model": 0.09
    },
    "ensemble": {
      "cf": 0.5389241339008085,
      "cg": 0.4556549479866782,
      "overall": 0.500909090909091
    },
    "features": {
      "latitude": 22.25,
      "longitude": 120.5
    }
  },
  {
    "date": "2023-06-22",
    "individual_predictions": {
      "cf_glm_model": 0.467,
      "cf_lda_model": 0.74,
      "cf_nn_model": 0.554,
      "cf_nn_nn_model": 0.251,
      "cf_rf_model": 0.66,
      "cf_svm_model": 0.511,
      "cg_glm_model": 0.482,
      "cg_lda_model": 0.728,
      "cg_nn_model": 0.556,
      "cg_rf_model": 0.18,
      "cg_svm_model": 0.093
    },
    "ensemble": {
      "cf": 0.5303887051277335,
      "cg": 0.4078899821645671,
      "overall": 0.4747272727272728
    },
    "features": {
      "latitude": 22.5,
      "longitude": 120.5
    }
  },
  {
    "date": "2023-06-22",
    "individual_predictions": {
      "cf_glm_model": 0.467,
      "cf_lda_model": 0.692,
      "cf_nn_model": 0.554,
      "cf_nn_nn_model": 0.251,
      "cf_rf_model": 0.669,
      "cf_svm_model": 0.51,
      "cg_glm_model": 0.482,
      "cg_lda_model": 0.729,
      "cg_nn_model": 0.556,
      "cg_rf_model": 0.17,
      "cg_svm_model": 0.093
    },
    "ensemble": {
      "cf": 0.5239265085710992,
      "cg": 0.40598102790535073,
      "overall": 0.4702727272727272
    },
    "features": {
      "latitude": 22.75,
      "longitude": 120.5
    }
  },
  {
    "date": "2023-06-22",
    "individual_predictions": {
      "cf_glm_model": 0.47,
      "cf_lda_model": 0.619,
      "cf_nn_model": 0.554,
      "cf_nn_nn_model": 0.251,
      "cf_rf_model": 0.665,
      "cf_svm_model": 0.519,
      "cg_glm_model": 0.457,
      "cg_lda_model": 0.646,
      "cg_nn_model": 0.556,
      "cg_rf_model": 0.255,
      "cg_svm_model": 0.1
    },
    "ensemble": {
      "cf": 0.5129709475025238,
      "cg": 0.4028468324112334,
      "overall": 0.4629090909090909
    },
    "features": {
      "latitude": 23.0,
      "longitude": 120.5
    }
  },
  {
    "date": "2023-06-22",
    "individual_predictions": {
      "cf_glm_model": 0.465,
      "cf_lda_model": 0.8,
      "cf_nn_model": 0.554,
      "cf_nn_nn_model": 0.251,
      "cf_rf_model": 0.623,
      "cf_svm_model": 0.494,
      "cg_glm_model": 0.522,
      "cg_lda_model": 0.367,
      "cg_nn_model": 0.729,
      "cg_rf_model": 0.215,
      "cg_svm_model": 0.083
    },
    "ensemble": {
      "cf": 0.5311283488186537,
      "cg": 0.3831815337189113,
      "overall": 0.463909090909091
    },
    "features": {
      "latitude": 23.25,
      "longitude": 120.5
    }
  },
  {
    "date": "2023-06-22",
    "individual_predictions": {
      "cf_glm_model": 0.465,
      "cf_lda_model": 0.69,
      "cf_nn_model": 0.554,
      "cf_nn_nn_model": 0.251,
      "cf_rf_model": 0.63,
      "cf_svm_model": 0.493,
      "cg_glm_model": 0.525,
      "cg_lda_model": 0.934,
      "cg_nn_model": 0.729,
      "cg_rf_model": 0.155,
      "cg_svm_model": 0.082
    },
    "ensemble": {
      "cf": 0.5137821708999591,
      "cg": 0.4848762530181122,
      "overall": 0.5007272727272727
    },
    "features": {
      "latitude": 23.5,
      "longitude": 120.5
    }
  },
  {
    "date": "2023-06-22",
    "individual_predictions": {
      "cf_glm_model": 0.465,
      "cf_lda_model": 0.73,
      "cf_nn_model": 0.554,
      "cf_nn_nn_model": 0.251,
      "cf_rf_model": 0.571,
      "cf_svm_model": 0.491,
      "cg_glm_model": 0.528,
      "cg_lda_model": 0.605,
      "cg_nn_model": 0.729,
      "cg_rf_model": 0.165,
      "cg_svm_model": 0.081
    },
    "ensemble": {
      "cf": 0.5102647698108583,
      "cg": 0.4214612216912035,
      "overall": 0.4700000000000001
    },
    "features": {
      "latitude": 23.75,
      "longitude": 120.5
    }
  },
  {
    "date": "2023-06-22",
    "individual_predictions": {
      "cf_glm_model": 0.468,
      "cf_lda_model": 0.804,
      "cf_nn_model": 0.554,
      "cf_nn_nn_model": 0.251,
      "cf_rf_model": 0.544,
      "cf_svm_model": 0.5,
      "cg_glm_model": 0.491,
      "cg_lda_model": 0.847,
      "cg_nn_model": 0.556,
      "cg_rf_model": 0.17,
      "cg_svm_model": 0.09
    },
    "ensemble": {
      "cf": 0.5201936815952392,
      "cg": 0.43093883601746896,
      "overall": 0.4795454545454545
    },
    "features": {
      "latitude": 24.0,
      "longitude": 120.5
    }
  },
  {
    "date": "2023-06-22",
    "individual_predictions": {
      "cf_glm_model": 0.472,
      "cf_lda_model": 0.815,
      "cf_nn_model": 0.554,
      "cf_nn_nn_model": 0.251,
      "cf_rf_model": 0.555,
      "cf_svm_model": 0.52,
      "cg_glm_model": 0.449,
      "cg_lda_model": 0.976,
      "cg_nn_model": 0.417,
      "cg_rf_model": 0.24,
      "cg_svm_model": 0.101
    },
    "ensemble": {
      "cf": 0.5278116918775176,
      "cg": 0.43651046974568597,
      "overall": 0.4863636363636364
    },
    "features": {
      "latitude": 24.25,
      "longitude": 120.5
    }
  },
  {
    "date": "2023-06-22",
    "individual_predictions": {
      "cf_glm_model": 0.473,
      "cf_lda_model": 0.807,
      "cf_nn_model": 0.554,
      "cf_nn_nn_model": 0.251,
      "cf_rf_model": 0.556,
      "cf_svm_model": 0.52,
      "cg_glm_model": 0.449,
      "cg_lda_model": 0.987,
      "cg_nn_model": 0.417,
      "cg_rf_model": 0.235,
      "cg_svm_model": 0.101
    },
    "ensemble": {
      "cf": 0.5266736991907485,
      "cg": 0.43768369228894644,
      "overall": 0.48636363636363633
    },
    "features": {
      "latitude": 24.5,
      "longitude": 120.5
    }
  },
  {
    "date": "2023-06-22",
    "individual_predictions": {
      "cf_glm_model": 0.461,
      "cf_lda_model": 0.917,
      "cf_nn_model": 0.554,
      "cf_nn_nn_model": 0.251,
      "cf_rf_model": 0.6,
      "cf_svm_model": 0.491,
      "cg_glm_model": 0.537,
      "cg_lda_model": 0.961,
      "cg_nn_model": 0.729,
      "cg_rf_model": 0.3,
      "cg_svm_model": 0.08
    },
    "ensemble": {
      "cf": 0.5456245581548466,
      "cg": 0.5213256773150394,
      "overall": 0.5346363636363637
    },
    "features": {
      "latitude": 21.75,
      "longitude": 120.75
    }
  },
  {
    "date": "2023-06-22",
    "individual_predictions": {
      "cf_glm_model": 0.463,
      "cf_lda_model": 0.91,
      "cf_nn_model": 0.554,
      "cf_nn_nn_model": 0.251,
      "cf_rf_model": 0.584,
      "cf_svm_model": 0.5,
      "cg_glm_model": 0.519,
      "cg_lda_model": 0.85,
      "cg_nn_model": 0.729,
      "cg_rf_model": 0.19,
      "cg_svm_model": 0.084
    },
    "ensemble": {
      "cf": 0.5436646260360963,
      "cg": 0.47442626255585363,
      "overall": 0.5121818181818182
    },
    "features": {
      "latitude": 22.0,
      "longitude": 120.75
    }
  },
  {
    "date": "2023-06-22",
    "individual_predictions": {
      "cf_glm_model": 0.469,
      "cf_lda_model": 0.902,
      "cf_nn_model": 0.554,
      "cf_nn_nn_model": 0.251,
      "cf_rf_model": 0.707,
      "cf_svm_model": 0.523,
      "cg_glm_model": 0.449,
      "cg_lda_model": 0.711,
      "cg_nn_model": 0.417,
      "cg_rf_model": 0.285,
      "cg_svm_model": 0.102
    },
    "ensemble": {
      "cf": 0.5678170273501225,
      "cg": 0.3927172817423916,
      "overall": 0.4881818181818182
    },
    "features": {
      "latitude": 22.25,
      "longitude": 120.75
    }
  },
  {
    "date": "2023-06-22",
    "individual_predictions": {
      "cf_glm_model": 0.482,
      "cf_lda_model": 0.975,
      "cf_nn_model": 0.443,
      "cf_nn_nn_model": 0.152,
      "cf_rf_model": 0.623,
      "cf_svm_model": 0.574,
      "cg_glm_model": 0.31,
      "cg_lda_model": 0.19,
      "cg_nn_model": 0.352,
      "cg_rf_model": 0.445,
      "cg_svm_model": 0.15
    },
    "ensemble": {
      "cf": 0.5414742311904457,
      "cg": 0.2893859740805359,
      "overall": 0.42690909090909096
    },
    "features": {
      "latitude": 22.5,
      "longitude": 120.75
    }
  },
  {
    "date": "2023-06-22",
    "individual_predictions": {
      "cf_glm_model": 0.474,
      "cf_lda_model": 0.84,
      "cf_nn_model": 0.554,
      "cf_nn_nn_model": 0.251,
      "cf_rf_model": 0.633,
      "cf_svm_model": 0.539,
      "cg_glm_model": 0.403,
      "cg_lda_model": 0.29,
      "cg_nn_model": 0.417,
      "cg_rf_model": 0.34,
      "cg_svm_model": 0.116
    },
    "ensemble": {
      "cf": 0.5486493286252726,
      "cg": 0.3129671864916087,
      "overall": 0.4415454545454546
    },
    "features": {
      "latitude": 22.75,
      "longitude": 120.75
    }
  },
  {
    "date": "2023-06-22",
    "individual_predictions": {
      "cf_glm_model": 0.482,
      "cf_lda_model": 0.963,
      "cf_nn_model": 0.443,
      "cf_nn_nn_model": 0.152,
      "cf_rf_model": 0.601,
      "cf_svm_model": 0.574,
      "cg_glm_model": 0.31,
      "cg_lda_model": 0.15,
      "cg_nn_model": 0.352,
      "cg_rf_model": 0.415,
      "cg_svm_model": 0.15
    },
    "ensemble": {
      "cf": 0.5358803731459015,
      "cg": 0.275218644530122,
      "overall": 0.4174545454545455
    },
    "features": {
      "latitude": 23.0,
      "longitude": 120.75
    }
  },
  {
    "date": "2023-06-22",
    "individual_predictions": {
      "cf_glm_model": 0.473,
      "cf_lda_model": 0.968,
      "cf_nn_model": 0.554,
      "cf_nn_nn_model": 0.251,
      "cf_rf_model": 0.448,
      "cf_svm_model": 0.529,
      "cg_glm_model": 0.43,
      "cg_lda_model": 0.014,
      "cg_nn_model": 0.417,
      "cg_rf_model": 0.315,
      "cg_svm_model": 0.107
    },
    "ensemble": {
      "cf": 0.5370787228496768,
      "cg": 0.25658942794475703,
      "overall": 0.40963636363636363
    },
    "features": {
      "latitude": 23.25,
      "longitude": 120.75
    }
  },
  {
    "date": "2023-06-22",
    "individual_predictions": {
      "cf_glm_model": 0.468,
      "cf_lda_model": 0.885,
      "cf_nn_model": 0.554,
      "cf_nn_nn_model": 0.251,
      "cf_rf_model": 0.457,
      "cf_svm_model": 0.507,
      "cg_glm_model": 0.487,
      "cg_lda_model": 0.204,
      "cg_nn_model": 0.556,
      "cg_rf_model": 0.265,
      "cg_svm_model": 0.092
    },
    "ensemble": {
      "cf": 0.5204271641823263,
      "cg": 0.32061332963297967,
      "overall": 0.42963636363636354
    },
    "features": {
      "latitude": 23.5,
      "longitude": 120.75
    }
  },
  {
    "date": "2023-06-22",
    "individual_predictions": {
      "cf_glm_model": 0.47,
      "cf_lda_model": 0.806,
      "cf_nn_model": 0.554,
      "cf_nn_nn_model": 0.251,
      "cf_rf_model": 0.645,
      "cf_svm_model": 0.515,
      "cg_glm_model": 0.465,
      "cg_lda_model": 0.724,
      "cg_nn_model": 0.556,
      "cg_rf_model": 0.22,
      "cg_svm_model": 0.097
    },
    "ensemble": {
      "cf": 0.5402588458052853,
      "cg": 0.41244517828585153,
      "overall": 0.48209090909090907
    },
    "features": {
      "latitude": 23.75,
      "longitude": 120.75
    }
  },
  {
    "date": "2023-06-22",
    "individual_predictions": {
      "cf_glm_model": 0.471,
      "cf_lda_model": 0.788,
      "cf_nn_model": 0.554,
      "cf_nn_nn_model": 0.251,
      "cf_rf_model": 0.635,
      "cf_svm_model": 0.515,
      "cg_glm_model": 0.465,
      "cg_lda_model": 0.791,
      "cg_nn_model": 0.556,
      "cg_rf_model": 0.225,
      "cg_svm_model": 0.097
    },
    "ensemble": {
      "cf": 0.5354587751048542,
      "cg": 0.42680112657156977,
      "overall": 0.48618181818181816
    },
    "features": {
      "latitude": 24.0,
      "longitude": 120.75
    }
  },
  {
    "date": "2023-06-22",
    "individual_predictions": {
      "cf_glm_model": 0.471,
      "cf_lda_model": 0.781,
      "cf_nn_model": 0.554,
      "cf_nn_nn_model": 0.251,
      "cf_rf_model": 0.677,
      "cf_svm_model": 0.514,
      "cg_glm_model": 0.464,
      "cg_lda_model": 0.816,
      "cg_nn_model": 0.556,
      "cg_rf_model": 0.23,
      "cg_svm_model": 0.097
    },
    "ensemble": {
      "cf": 0.5414676621861775,
      "cg": 0.43280915048911217,
      "overall": 0.491909090909091
    },
    "features": {
      "latitude": 24.25,
      "longitude": 120.75
    }
  },
  {
    "date": "2023-06-22",
    "individual_predictions": {
      "cf_glm_model": 0.475,
      "cf_lda_model": 0.832,
      "cf_nn_model": 0.554,
      "cf_nn_nn_model": 0.251,
      "cf_rf_model": 0.605,
      "cf_svm_model": 0.527,
      "cg_glm_model": 0.429,
      "cg_lda_model": 0.978,
      "cg_nn_model": 0.417,
      "cg_rf_model": 0.2,
      "cg_svm_model": 0.107
    },
    "ensemble": {
      "cf": 0.5405411827104579,
      "cg": 0.4261136192573279,
      "overall": 0.48863636363636365
    },
    "features": {
      "latitude": 24.5,
      "longitude": 120.75
    }
  },
  {
    "date": "2023-06-22",
    "individual_predictions": {
      "cf_glm_model": 0.475,
      "cf_lda_model": 0.827,
      "cf_nn_model": 0.554,
      "cf_nn_nn_model": 0.251,
      "cf_rf_model": 0.59,
      "cf_svm_model": 0.527,
      "cg_glm_model": 0.428,
      "cg_lda_model": 0.986,
      "cg_nn_model": 0.417,
      "cg_rf_model": 0.275,
      "cg_svm_model": 0.107
    },
    "ensemble": {
      "cf": 0.5372576280348376,
      "cg": 0.44252184743327144,
      "overall": 0.4942727272727273
    },
    "features": {
      "latitude": 24.75,
      "longitude": 120.75
    }
  },
  {
    "date": "2023-06-22",
    "individual_predictions": {
      "cf_glm_model": 0.462,
      "cf_lda_model": 0.924,
      "cf_nn_model": 0.554,
      "cf_nn_nn_model": 0.251,
      "cf_rf_model": 0.601,
      "cf_svm_model": 0.495,
      "cg_glm_model": 0.527,
      "cg_lda_model": 0.96,
      "cg_nn_model": 0.729,
      "cg_rf_model": 0.345,
      "cg_svm_model": 0.082
    },
    "ensemble": {
      "cf": 0.5477000491285174,
      "cg": 0.5286180794509339,
      "overall": 0.5390909090909092
    },
    "features": {
      "latitude": 21.75,
      "longitude": 121.0
    }
  },
  {
    "date": "2023-06-22",
    "individual_predictions": {
      "cf_glm_model": 0.464,
      "cf_lda_model": 0.92,
      "cf_nn_model": 0.554,
      "cf_nn_nn_model": 0.251,
      "cf_rf_model": 0.635,
      "cf_svm_model": 0.5,
      "cg_glm_model": 0.504,
      "cg_lda_model": 0.988,
      "cg_nn_model": 0.729,
      "cg_rf_model": 0.33,
      "cg_svm_model": 0.088
    },
    "ensemble": {
      "cf": 0.553990967550297,
      "cg": 0.5277791526049307,
      "overall": 0.5420909090909091
    },
    "features": {
      "latitude": 22.0,
      "longitude": 121.0
    }
  },
  {
    "date": "2023-06-22",
    "individual_predictions": {
      "cf_glm_model": 0.471,
      "cf_lda_model": 0.93,
      "cf_nn_model": 0.554,
      "cf_nn_nn_model": 0.251,
      "cf_rf_model": 0.668,
      "cf_svm_model": 0.534,
      "cg_glm_model": 0.419,
      "cg_lda_model": 0.811,
      "cg_nn_model": 0.417,
      "cg_rf_model": 0.475,
      "cg_svm_model": 0.111
    },
    "ensemble": {
      "cf": 0.5679020083088202,
      "cg": 0.4465981162818758,
      "overall": 0.5128181818181817
    },
    "features": {
      "latitude": 22.25,
      "longitude": 121.0
    }
  },
  {
    "date": "2023-06-22",
    "individual_predictions": {
      "cf_glm_model": 0.472,
      "cf_lda_model": 0.909,
      "cf_nn_model": 0.554,
      "cf_nn_nn_model": 0.251,
      "cf_rf_model": 0.621,
      "cf_svm_model": 0.534,
      "cg_glm_model": 0.419,
      "cg_lda_model": 0.614,
      "cg_nn_model": 0.417,
      "cg_rf_model": 0.45,
      "cg_svm_model": 0.111
    },
    "ensemble": {
      "cf": 0.5567244341271606,
      "cg": 0.40210560580275184,
      "overall": 0.4865454545454545
    },
    "features": {
      "latitude": 22.5,
      "longitude": 121.0
    }
  },
  {
    "date": "2023-06-22",
    "individual_predictions": {
      "cf_glm_model": 0.474,
      "cf_lda_model": 0.788,
      "cf_nn_model": 0.554,
      "cf_nn_nn_model": 0.251,
      "cf_rf_model": 0.662,
      "cf_svm_model": 0.539,
      "cg_glm_model": 0.404,
      "cg_lda_model": 0.362,
      "cg_nn_model": 0.417,
      "cg_rf_model": 0.375,
      "cg_svm_model": 0.115
    },
    "ensemble": {
      "cf": 0.5444952033058881,
      "cg": 0.3346288047112761,
      "overall": 0.44918181818181824
    },
    "features": {
      "latitude": 22.75,
      "longitude": 121.0
    }
  },
  {
    "date": "2023-06-22",
    "individual_predictions": {
      "cf_glm_model": 0.475,
      "cf_lda_model": 0.972,
      "cf_nn_model": 0.554,
      "cf_nn_nn_model": 0.251,
      "cf_rf_model": 0.378,
      "cf_svm_model": 0.537,
      "cg_glm_model": 0.409,
      "cg_lda_model": 0.003,
      "cg_nn_model": 0.417,
      "cg_rf_model": 0.36,
      "cg_svm_model": 0.114
    },
    "ensemble": {
      "cf": 0.5276989777685891,
      "cg": 0.26040288972761905,
      "overall": 0.4063636363636363
    },
    "features": {
      "latitude": 23.0,
      "longitude": 121.0
    }
  },
  {
    "date": "2023-06-22",
    "individual_predictions": {
      "cf_glm_model": 0.473,
      "cf_lda_model": 0.982,
      "cf_nn_model": 0.554,
      "cf_nn_nn_model": 0.251,
      "cf_rf_model": 0.385,
      "cf_svm_model": 0.528,
      "cg_glm_model": 0.431,
      "cg_lda_model": 0.003,
      "cg_nn_model": 0.417,
      "cg_rf_model": 0.335,
      "cg_svm_model": 0.107
    },
    "ensemble": {
      "cf": 0.5289245387920168,
      "cg": 0.2585150568651008,
      "overall": 0.406
    },
    "features": {
      "latitude": 23.25,
      "longitude": 121.0
    }
  },
  {
    "date": "2023-06-22",
    "individual_predictions": {
      "cf_glm_model": 0.474,
      "cf_lda_model": 0.981,
      "cf_nn_model": 0.554,
      "cf_nn_nn_model": 0.251,
      "cf_rf_model": 0.431,
      "cf_svm_model": 0.528,
      "cg_glm_model": 0.431,
      "cg_lda_model": 0.002,
      "cg_nn_model": 0.417,
      "cg_rf_model": 0.35,
      "cg_svm_model": 0.107
    },
    "ensemble": {
      "cf": 0.5364305405139311,
      "cg": 0.26134768089241145,
      "overall": 0.41145454545454546
    },
    "features": {
      "latitude": 23.5,
      "longitude": 121.0
    }
  },
  {
    "date": "2023-06-22",
    "individual_predictions": {
      "cf_glm_model": 0.474,
      "cf_lda_model": 0.976,
      "cf_nn_model": 0.554,
      "cf_nn_nn_model": 0.251,
      "cf_rf_model": 0.431,
      "cf_svm_model": 0.528,
      "cg_glm_model": 0.431,
      "cg_lda_model": 0.009,
      "cg_nn_model": 0.417,
      "cg_rf_model": 0.33,
      "cg_svm_model": 0.107
    },
    "ensemble": {
      "cf": 0.5355256446873073,
      "cg": 0.2587205524893242,
      "overall": 0.4098181818181818
    },
    "features": {
      "latitude": 23.75,
      "longitude": 121.0
    }
  },
  {
    "date": "2023-06-22",
    "individual_predictions": {
      "cf_glm_model": 0.475,
      "cf_lda_model": 0.923,
      "cf_nn_model": 0.554,
      "cf_nn_nn_model": 0.251,
      "cf_rf_model": 0.566,
      "cf_svm_model": 0.532,
      "cg_glm_model": 0.418,
      "cg_lda_model": 0.626,
      "cg_nn_model": 0.417,
      "cg_rf_model": 0.285,
      "cg_svm_model": 0.11
    },
    "ensemble": {
      "cf": 0.5501360415940628,
      "cg": 0.37126478488376746,
      "overall": 0.4688181818181819
    },
    "features": {
      "latitude": 24.0,
      "longitude": 121.0
    }
  },
  {
    "date": "2023-06-22",
    "individual_predictions": {
      "cf_glm_model": 0.487,
      "cf_lda_model": 0.981,
      "cf_nn_model": 0.443,
      "cf_nn_nn_model": 0.152,
      "cf_rf_model": 0.443,
      "cf_svm_model": 0.58,
      "cg_glm_model": 0.287,
      "cg_lda_model": 0.119,
      "cg_nn_model": 0.414,
      "cg_rf_model": 0.385,
      "cg_svm_model": 0.159
    },
    "ensemble": {
      "cf": 0.5144998654629004,
      "cg": 0.27267245788551814,
      "overall": 0.4045454545454545
    },
    "features": {
      "latitude": 24.25,
      "longitude": 121.0
    }
  },
  {
    "date": "2023-06-22",
    "individual_predictions": {
      "cf_glm_model": 0.49,
      "cf_lda_model": 0.979,
      "cf_nn_model": 0.443,
      "cf_nn_nn_model": 0.152,
      "cf_rf_model": 0.332,
      "cf_svm_model": 0.587,
      "cg_glm_model": 0.269,
      "cg_lda_model": 0.107,
      "cg_nn_model": 0.414,
      "cg_rf_model": 0.385,
      "cg_svm_model": 0.167
    },
    "ensemble": {
      "cf": 0.49711087404504856,
      "cg": 0.2683356756284365,
      "overall": 0.3931818181818182
    },
    "features": {
      "latitude": 24.5,
      "longitude": 121.0
    }
  },
  {
    "date": "2023-06-22",
    "individual_predictions": {
      "cf_glm_model": 0.502,
      "cf_lda_model": 0.894,
      "cf_nn_model": 0.297,
      "cf_nn_nn_model": 0.102,
      "cf_rf_model": 0.676,
      "cf_svm_model": 0.629,
      "cg_glm_model": 0.172,
      "cg_lda_model": 0.993,
      "cg_nn_model": 0.468,
      "cg_rf_model": 0.54,
      "cg_svm_model": 0.225
    },
    "ensemble": {
      "cf": 0.5166035955241509,
      "cg": 0.47950399301227425,
      "overall": 0.49981818181818183
    },
    "features": {
      "latitude": 24.75,
      "longitude": 121.0
    }
  },
  {
    "date": "2023-06-22",
    "individual_predictions": {
      "cf_glm_model": 0.502,
      "cf_lda_model": 0.902,
      "cf_nn_model": 0.297,
      "cf_nn_nn_model": 0.102,
      "cf_rf_model": 0.529,
      "cf_svm_model": 0.628,
      "cg_glm_model": 0.172,
      "cg_lda_model": 0.985,
      "cg_nn_model": 0.468,
      "cg_rf_model": 0.51,
      "cg_svm_model": 0.225
    },
    "ensemble": {
      "cf": 0.4933020011774109,
      "cg": 0.47194060064805027,
      "overall": 0.4836363636363636
    },
    "features": {
      "latitude": 25.0,
      "longitude": 121.0
    }
  },
  {
    "date": "2023-06-22",
    "individual_predictions": {
      "cf_glm_model": 0.463,
      "cf_lda_model": 0.919,
      "cf_nn_model": 0.554,
      "cf_nn_nn_model": 0.251,
      "cf_rf_model": 0.606,
      "cf_svm_model": 0.5,
      "cg_glm_model": 0.511,
      "cg_lda_model": 0.925,
      "cg_nn_model": 0.729,
      "cg_rf_model": 0.345,
      "cg_svm_model": 0.086
    },
    "ensemble": {
      "cf": 0.5489409316526146,
      "cg": 0.519205146797258,
      "overall": 0.5353636363636364
    },
    "features": {
      "latitude": 21.75,
      "longitude": 121.25
    }
  },
  {
    "date": "2023-06-22",
    "individual_predictions": {
      "cf_glm_model": 0.465,
      "cf_lda_model": 0.948,
      "cf_nn_model": 0.554,
      "cf_nn_nn_model": 0.251,
      "cf_rf_model": 0.624,
      "cf_svm_model": 0.508,
      "cg_glm_model": 0.492,
      "cg_lda_model": 0.983,
      "cg_nn_model": 0.556,
      "cg_rf_model": 0.325,
      "cg_svm_model": 0.091
    },
    "ensemble": {
      "cf": 0.5584148877572118,
      "cg": 0.4893607671307527,
      "overall": 0.527
    },
    "features": {
      "latitude": 22.0,
      "longitude": 121.25
    }
  },
  {
    "date": "2023-06-22",
    "individual_predictions": {
      "cf_glm_model": 0.471,
      "cf_lda_model": 0.925,
      "cf_nn_model": 0.554,
      "cf_nn_nn_model": 0.251,
      "cf_rf_model": 0.673,
      "cf_svm_model": 0.534,
      "cg_glm_model": 0.42,
      "cg_lda_model": 0.81,
      "cg_nn_model": 0.417,
      "cg_rf_model": 0.475,
      "cg_svm_model": 0.111
    },
    "ensemble": {
      "cf": 0.5679236253332828,
      "cg": 0.4464758017642193,
      "overall": 0.5128181818181817
    },
    "features": {
      "latitude": 22.25,
      "longitude": 121.25
    }
  },
  {
    "date": "2023-06-22",
    "individual_predictions": {
      "cf_glm_model": 0.472,
      "cf_lda_model": 0.93,
      "cf_nn_model": 0.554,
      "cf_nn_nn_model": 0.251,
      "cf_rf_model": 0.668,
      "cf_svm_model": 0.533,
      "cg_glm_model": 0.42,
      "cg_lda_model": 0.795,
      "cg_nn_model": 0.417,
      "cg_rf_model": 0.475,
      "cg_svm_model": 0.111
    },
    "ensemble": {
      "cf": 0.5679178176413848,
      "cg": 0.4435530418991324,
      "overall": 0.5114545454545455
    },
    "features": {
      "latitude": 22.5,
      "longitude": 121.25
    }
  },
  {
    "date": "2023-06-22",
    "individual_predictions": {
      "cf_glm_model": 0.472,
      "cf_lda_model": 0.876,
      "cf_nn_model": 0.554,
      "cf_nn_nn_model": 0.251,
      "cf_rf_model": 0.556,
      "cf_svm_model": 0.533,
      "cg_glm_model": 0.421,
      "cg_lda_model": 0.944,
      "cg_nn_model": 0.417,
      "cg_rf_model": 0.435,
      "cg_svm_model": 0.11
    },
    "ensemble": {
      "cf": 0.5402665541204402,
      "cg": 0.4652728437205001,
      "overall": 0.5062727272727272
    },
    "features": {
      "latitude": 22.75,
      "longitude": 121.25
    }
  },
  {
    "date": "2023-06-22",
    "individual_predictions": {
      "cf_glm_model": 0.486,
      "cf_lda_model": 0.889,
      "cf_nn_model": 0.443,
      "cf_nn_nn_model": 0.152,
      "cf_rf_model": 0.451,
      "cf_svm_model": 0.587,
      "cg_glm_model": 0.274,
      "cg_lda_model": 0.236,
      "cg_nn_model": 0.414,
      "cg_rf_model": 0.53,
      "cg_svm_model": 0.165
    },
    "ensemble": {
      "cf": 0.5012986933404925,
      "cg": 0.3237924431544854,
      "overall": 0.42063636363636364
    },
    "features": {
      "latitude": 23.0,
      "longitude": 121.25
    }
  },
  {
    "date": "2023-06-22",
    "individual_predictions": {
      "cf_glm_model": 0.487,
      "cf_lda_model": 0.888,
      "cf_nn_model": 0.443,
      "cf_nn_nn_model": 0.152,
      "cf_rf_model": 0.56,
      "cf_svm_model": 0.588,
      "cg_glm_model": 0.272,
      "cg_lda_model": 0.028,
      "cg_nn_model": 0.414,
      "cg_rf_model": 0.393,
      "cg_svm_model": 0.167
    },
    "ensemble": {
      "cf": 0.5196620432533189,
      "cg": 0.25454501217935954,
      "overall": 0.3992727272727273
    },
    "features": {
      "latitude": 23.25,
      "longitude": 121.25
    }
  },
  {
    "date": "2023-06-22",
    "individual_predictions": {
      "cf_glm_model": 0.487,
      "cf_lda_model": 0.893,
      "cf_nn_model": 0.443,
      "cf_nn_nn_model": 0.152,
      "cf_rf_model": 0.542,
      "cf_svm_model": 0.587,
      "cg_glm_model": 0.272,
      "cg_lda_model": 0.039,
      "cg_nn_model": 0.414,
      "cg_rf_model": 0.428,
      "cg_svm_model": 0.166
    },
    "ensemble": {
      "cf": 0.5173054102719419,
      "cg": 0.2638286582841381,
      "overall": 0.40209090909090917
    },
    "features": {
      "latitude": 23.5,
      "longitude": 121.25
    }
  },
  {
    "date": "2023-06-22",
    "individual_predictions": {
      "cf_glm_model": 0.474,
      "cf_lda_model": 0.974,
      "cf_nn_model": 0.554,
      "cf_nn_nn_model": 0.251,
      "cf_rf_model": 0.406,
      "cf_svm_model": 0.528,
      "cg_glm_model": 0.431,
      "cg_lda_model": 0.002,
      "cg_nn_model": 0.417,
      "cg_rf_model": 0.365,
      "cg_svm_model": 0.107
    },
    "ensemble": {
      "cf": 0.5309244350042323,
      "cg": 0.2643525513132514,
      "overall": 0.40990909090909095
    },
    "features": {
      "latitude": 23.75,
      "longitude": 121.25
    }
  },
  {
    "date": "2023-06-22",
    "individual_predictions": {
      "cf_glm_model": 0.489,
      "cf_lda_model": 0.984,
      "cf_nn_model": 0.443,
      "cf_nn_nn_model": 0.152,
      "cf_rf_model": 0.335,
      "cf_svm_model": 0.588,
      "cg_glm_model": 0.269,
      "cg_lda_model": 0.018,
      "cg_nn_model": 0.414,
      "cg_rf_model": 0.41,
      "cg_svm_model": 0.167
    },
    "ensemble": {
      "cf": 0.4983817186424229,
      "cg": 0.2557116087561587,
      "overall": 0.38809090909090904
    },
    "features": {
      "latitude": 24.0,
      "longitude": 121.25
    }
  },
  {
    "date": "2023-06-22",
    "individual_predictions": {
      "cf_glm_model": 0.49,
      "cf_lda_model": 0.98,
      "cf_nn_model": 0.443,
      "cf_nn_nn_model": 0.152,
      "cf_rf_model": 0.354,
      "cf_svm_model": 0.586,
      "cg_glm_model": 0.271,
      "cg_lda_model": 0.028,
      "cg_nn_model": 0.414,
      "cg_rf_model": 0.385,
      "cg_svm_model": 0.166
    },
    "ensemble": {
      "cf": 0.5007854813182645,
      "cg": 0.25266271368954446,
      "overall": 0.3880909090909091
    },
    "features": {
      "latitude": 24.25,
      "longitude": 121.25
    }
  },
  {
    "date": "2023-06-22",
    "individual_predictions": {
      "cf_glm_model": 0.49,
      "cf_lda_model": 0.98,
      "cf_nn_model": 0.443,
      "cf_nn_nn_model": 0.152,
      "cf_rf_model": 0.36,
      "cf_svm_model": 0.586,
      "cg_glm_model": 0.271,
      "cg_lda_model": 0.037,
      "cg_nn_model": 0.414,
      "cg_rf_model": 0.375,
      "cg_svm_model": 0.166
    },
    "ensemble": {
      "cf": 0.5018288788626875,
      "cg": 0.25244469072608056,
      "overall": 0.38854545454545464
    },
    "features": {
      "latitude": 24.5,
      "longitude": 121.25
    }
  },
  {
    "date": "2023-06-22",
    "individual_predictions": {
      "cf_glm_model": 0.494,
      "cf_lda_model": 0.892,
      "cf_nn_model": 0.443,
      "cf_nn_nn_model": 0.152,
      "cf_rf_model": 0.805,
      "cf_svm_model": 0.601,
      "cg_glm_model": 0.233,
      "cg_lda_model": 0.922,
      "cg_nn_model": 0.419,
      "cg_rf_model": 0.46,
      "cg_svm_model": 0.186
    },
    "ensemble": {
      "cf": 0.5645141814581839,
      "cg": 0.44380910788392836,
      "overall": 0.5097272727272727
    },
    "features": {
      "latitude": 24.75,
      "longitude": 121.25
    }
  },
  {
    "date": "2023-06-22",
    "individual_predictions": {
      "cf_glm_model": 0.502,
      "cf_lda_model": 0.884,
      "cf_nn_model": 0.297,
      "cf_nn_nn_model": 0.102,
      "cf_rf_model": 0.708,
      "cf_svm_model": 0.628,
      "cg_glm_model": 0.172,
      "cg_lda_model": 0.992,
      "cg_nn_model": 0.468,
      "cg_rf_model": 0.545,
      "cg_svm_model": 0.225
    },
    "ensemble": {
      "cf": 0.5201949543210228,
      "cg": 0.4804697624318431,
      "overall": 0.502090909090909
    },
    "features": {
      "latitude": 25.0,
      "longitude": 121.25
    }
  },
  {
    "date": "2023-06-22",
    "individual_predictions": {
      "cf_glm_model": 0.516,
      "cf_lda_model": 0.87,
      "cf_nn_model": 0.603,
      "cf_nn_nn_model": 0.283,
      "cf_rf_model": 0.511,
      "cf_svm_model": 0.662,
      "cg_glm_model": 0.1,
      "cg_lda_model": 0.987,
      "cg_nn_model": 0.468,
      "cg_rf_model": 0.49,
      "cg_svm_model": 0.295
    },
    "ensemble": {
      "cf": 0.5739886375852744,
      "cg": 0.4679077703393831,
      "overall": 0.5259090909090909
    },
    "features": {
      "latitude": 25.25,
      "longitude": 121.25
    }
  },
  {
    "date": "2023-06-22",
    "individual_predictions": {
      "cf_glm_model": 0.47,
      "cf_lda_model": 0.941,
      "cf_nn_model": 0.554,
      "cf_nn_nn_model": 0.251,
      "cf_rf_model": 0.605,
      "cf_svm_model": 0.532,
      "cg_glm_model": 0.426,
      "cg_lda_model": 0.807,
      "cg_nn_model": 0.417,
      "cg_rf_model": 0.415,
      "cg_svm_model": 0.109
    },
    "ensemble": {
      "cf": 0.5587705946452693,
      "cg": 0.4347539590241046,
      "overall": 0.5024545454545455
    },
    "features": {
      "latitude": 22.0,
      "longitude": 121.5
    }
  },
  {
    "date": "2023-06-22",
    "individual_predictions": {
      "cf_glm_model": 0.473,
      "cf_lda_model": 0.962,
      "cf_nn_model": 0.554,
      "cf_nn_nn_model": 0.251,
      "cf_rf_model": 0.623,
      "cf_svm_model": 0.54,
      "cg_glm_model": 0.402,
      "cg_lda_model": 0.842,
      "cg_nn_model": 0.417,
      "cg_rf_model": 0.41,
      "cg_svm_model": 0.116
    },
    "ensemble": {
      "cf": 0.5672512897908285,
      "cg": 0.4373494696787432,
      "overall": 0.5081818181818182
    },
    "features": {
      "latitude": 22.25,
      "longitude": 121.5
    }
  },
  {
    "date": "2023-06-22",
    "individual_predictions": {
      "cf_glm_model": 0.476,
      "cf_lda_model": 0.967,
      "cf_nn_model": 0.554,
      "cf_nn_nn_model": 0.251,
      "cf_rf_model": 0.632,
      "cf_svm_model": 0.553,
      "cg_glm_model": 0.366,
      "cg_lda_model": 0.804,
      "cg_nn_model": 0.352,
      "cg_rf_model": 0.52,
      "cg_svm_model": 0.128
    },
    "ensemble": {
      "cf": 0.5721966762347416,
      "cg": 0.43404184710499133,
      "overall": 0.5093636363636364
    },
    "features": {
      "latitude": 22.5,
      "longitude": 121.5
    }
  }
]