[
  {
    "date": "2023-05-29",
    "individual_predictions": {
      "cf_glm_model": 0.519,
      "cf_lda_model": 0.904,
      "cf_nn_model": 0.554,
      "cf_nn_nn_model": 0.251,
      "cf_rf_model": 0.87,
      "cf_svm_model": 0.844,
      "cg_glm_model": 0.522,
      "cg_lda_model": 1.0,
      "cg_nn_model": 0.556,
      "cg_rf_model": 0.598,
      "cg_svm_model": 0.536
    },
    "ensemble": {
      "cf": 0.6570017940026287,
      "cg": 0.6426064614526251,
      "overall": 0.6503636363636364
    },
    "features": {
      "latitude": 23.25,
      "longitude": 119.25
    }
  },
  {
    "date": "2023-05-29",
    "individual_predictions": {
      "cf_glm_model": 0.514,
      "cf_lda_model": 0.904,
      "cf_nn_model": 0.364,
      "cf_nn_nn_model": 0.155,
      "cf_rf_model": 0.851,
      "cf_svm_model": 0.837,
      "cg_glm_model": 0.576,
      "cg_lda_model": 1.0,
      "cg_nn_model": 0.729,
      "cg_rf_model": 0.603,
      "cg_svm_model": 0.5
    },
    "ensemble": {
      "cf": 0.6040793359814999,
      "cg": 0.6815195617119462,
      "overall": 0.6393636363636364
    },
    "features": {
      "latitude": 23.25,
      "longitude": 119.5
    }
  },
  {
    "date": "2023-05-29",
    "individual_predictions": {
      "cf_glm_model": 0.518,
      "cf_lda_model": 0.899,
      "cf_nn_model": 0.554,
      "cf_nn_nn_model": 0.251,
      "cf_rf_model": 0.871,
      "cf_svm_model": 0.842,
      "cg_glm_model": 0.541,
      "cg_lda_model": 1.0,
      "cg_nn_model": 0.556,
      "cg_rf_model": 0.608,
      "cg_svm_model": 0.526
    },
    "ensemble": {
      "cf": 0.6557157222744072,
      "cg": 0.646255003586132,
      "overall": 0.6514545454545454
    },
    "features": {
      "latitude": 23.5,
      "longitude": 119.5
    }
  },
  {
    "date": "2023-05-29",
    "individual_predictions": {
      "cf_glm_model": 0.521,
      "cf_lda_model": 0.904,
      "cf_nn_model": 0.554,
      "cf_nn_nn_model": 0.251,
      "cf_rf_model": 0.854,
      "cf_svm_model": 0.845,
      "cg_glm_model": 0.513,
      "cg_lda_model": 1.0,
      "cg_nn_model": 0.556,
      "cg_rf_model": 0.59,
      "cg_svm_model": 0.542
    },
    "ensemble": {
      "cf": 0.6547813849494665,
      "cg": 0.6403193379778951,
      "overall": 0.6481818181818182
    },
    "features": {
      "latitude": 23.75,
      "longitude": 119.5
    }
  },
  {
    "date": "2023-05-29",
    "individual_predictions": {
      "cf_glm_model": 0.512,
      "cf_lda_model": 0.909,
      "cf_nn_model": 0.364,
      "cf_nn_nn_model": 0.155,
      "cf_rf_model": 0.821,
      "cf_svm_model": 0.833,
      "cg_glm_model": 0.601,
      "cg_lda_model": 1.0,
      "cg_nn_model": 0.729,
      "cg_rf_model": 0.608,
      "cg_svm_model": 0.489
    },
    "ensemble": {
      "cf": 0.598868285786593,
      "cg": 0.6852930909246291,
      "overall": 0.6382727272727272
    },
    "features": {
      "latitude": 23.25,
      "longitude": 119.75
    }
  },
  {
    "date": "2023-05-29",
    "individual_predictions": {
      "cf_glm_model": 0.515,
      "cf_lda_model": 0.899,
      "cf_nn_model": 0.554,
      "cf_nn_nn_model": 0.251,
      "cf_rf_model": 0.827,
      "cf_svm_model": 0.838,
      "cg_glm_model": 0.567,
      "cg_lda_model": 1.0,
      "cg_nn_model": 0.729,
      "cg_rf_model": 0.593,
      "cg_svm_model": 0.51
    },
    "ensemble": {
      "cf": 0.6473276845235035,
      "cg": 0.6798378401945753,
      "overall": 0.6620909090909092
    },
    "features": {
      "latitude": 23.5,
      "longitude": 119.75
    }
  },
  {
    "date": "2023-05-29",
    "individual_predictions": {
      "cf_glm_model": 0.517,
      "cf_lda_model": 0.903,
      "cf_nn_model": 0.554,
      "cf_nn_nn_model": 0.251,
      "cf_rf_model": 0.859,
      "cf_svm_model": 0.84,
      "cg_glm_model": 0.555,
      "cg_lda_model": 1.0,
      "cg_nn_model": 0.729,
      "cg_rf_model": 0.583,
      "cg_svm_model": 0.518
    },
    "ensemble": {
      "cf": 0.6539100607008307,
      "cg": 0.6769646827840863,
      "overall": 0.6644545454545455
    },
    "features": {
      "latitude": 23.75,
      "longitude": 119.75
    }
  },
  {
    "date": "2023-05-29",
    "individual_predictions": {
      "cf_glm_model": 0.513,
      "cf_lda_model": 0.93,
      "cf_nn_model": 0.554,
      "cf_nn_nn_model": 0.251,
      "cf_rf_model": 0.623,
      "cf_svm_model": 0.837,
      "cg_glm_model": 0.572,
      "cg_lda_model": 0.846,
      "cg_nn_model": 0.729,
      "cg_rf_model": 0.46,
      "cg_svm_model": 0.506
    },
    "ensemble": {
      "cf": 0.6181093590120716,
      "cg": 0.6226371818046852,
      "overall": 0.6200909090909091
    },
    "features": {
      "latitude": 22.75,
      "longitude": 120.0
    }
  },
  {
    "date": "2023-05-29",
    "individual_predictions": {
      "cf_glm_model": 0.509,
      "cf_lda_model": 0.938,
      "cf_nn_model": 0.364,
      "cf_nn_nn_model": 0.155,
      "cf_rf_model": 0.743,
      "cf_svm_model": 0.829,
      "cg_glm_model": 0.625,
      "cg_lda_model": 0.842,
      "cg_nn_model": 0.729,
      "cg_rf_model": 0.445,
      "cg_svm_model": 0.473
    },
    "ensemble": {
      "cf": 0.5895794151572357,
      "cg": 0.6226157416966778,
      "overall": 0.6047272727272728
    },
    "features": {
      "latitude": 23.0,
      "longitude": 120.0
    }
  },
  {
    "date": "2023-05-29",
    "individual_predictions": {
      "cf_glm_model": 0.51,
      "cf_lda_model": 0.915,
      "cf_nn_model": 0.364,
      "cf_nn_nn_model": 0.155,
      "cf_rf_model": 0.862,
      "cf_svm_model": 0.83,
      "cg_glm_model": 0.621,
      "cg_lda_model": 0.881,
      "cg_nn_model": 0.729,
      "cg_rf_model": 0.425,
      "cg_svm_model": 0.476
    },
    "ensemble": {
      "cf": 0.6059776954450163,
      "cg": 0.6262128975445334,
      "overall": 0.6152727272727273
    },
    "features": {
      "latitude": 23.25,
      "longitude": 120.0
    }
  },
  {
    "date": "2023-05-29",
    "individual_predictions": {
      "cf_glm_model": 0.511,
      "cf_lda_model": 0.922,
      "cf_nn_model": 0.364,
      "cf_nn_nn_model": 0.155,
      "cf_rf_model": 0.872,
      "cf_svm_model": 0.83,
      "cg_glm_model": 0.621,
      "cg_lda_model": 0.871,
      "cg_nn_model": 0.729,
      "cg_rf_model": 0.425,
      "cg_svm_model": 0.476
    },
    "ensemble": {
      "cf": 0.6087764730432322,
      "cg": 0.6243629800417003,
      "overall": 0.616
    },
    "features": {
      "latitude": 23.5,
      "longitude": 120.0
    }
  },
  {
    "date": "2023-05-29",
    "individual_predictions": {
      "cf_glm_model": 0.511,
      "cf_lda_model": 0.929,
      "cf_nn_model": 0.364,
      "cf_nn_nn_model": 0.155,
      "cf_rf_model": 0.867,
      "cf_svm_model": 0.83,
      "cg_glm_model": 0.622,
      "cg_lda_model": 0.861,
      "cg_nn_model": 0.729,
      "cg_rf_model": 0.425,
      "cg_svm_model": 0.476
    },
    "ensemble": {
      "cf": 0.6092474853069838,
      "cg": 0.6225458545006968,
      "overall": 0.6153636363636363
    },
    "features": {
      "latitude": 23.75,
      "longitude": 120.0
    }
  },
  {
    "date": "2023-05-29",
    "individual_predictions": {
      "cf_glm_model": 0.513,
      "cf_lda_model": 0.923,
      "cf_nn_model": 0.364,
      "cf_nn_nn_model": 0.155,
      "cf_rf_model": 0.772,
      "cf_svm_model": 0.832,
      "cg_glm_model": 0.608,
      "cg_lda_model": 0.989,
      "cg_nn_model": 0.729,
      "cg_rf_model": 0.6,
      "cg_svm_model": 0.486
    },
    "ensemble": {
      "cf": 0.5929767161168904,
      "cg": 0.6821956665011674,
      "overall": 0.6337272727272727
    },
    "features": {
      "latitude": 24.0,
      "longitude": 120.0
    }
  },
  {
    "date": "2023-05-29",
    "individual_predictions": {
      "cf_glm_model": 0.512,
      "cf_lda_model": 0.914,
      "cf_nn_model": 0.364,
      "cf_nn_nn_model": 0.155,
      "cf_rf_model": 0.682,
      "cf_svm_model": 0.836,
      "cg_glm_model": 0.578,
      "cg_lda_model": 0.907,
      "cg_nn_model": 0.729,
      "cg_rf_model": 0.515,
      "cg_svm_model": 0.5
    },
    "ensemble": {
      "cf": 0.5769840904511455,
      "cg": 0.6459117721187527,
      "overall": 0.6083636363636363
    },
    "features": {
      "latitude": 22.25,
      "longitude": 120.25
    }
  },
  {
    "date": "2023-05-29",
    "individual_predictions": {
      "cf_glm_model": 0.513,
      "cf_lda_model": 0.919,
      "cf_nn_model": 0.554,
      "cf_nn_nn_model": 0.251,
      "cf_rf_model": 0.743,
      "cf_svm_model": 0.837,
      "cg_glm_model": 0.572,
      "cg_lda_model": 0.686,
      "cg_nn_model": 0.729,
      "cg_rf_model": 0.428,
      "cg_svm_model": 0.506
    },
    "ensemble": {
      "cf": 0.6360718491113883,
      "cg": 0.5842019262474938,
      "overall": 0.6125454545454546
    },
    "features": {
      "latitude": 22.5,
      "longitude": 120.25
    }
  },
  {
    "date": "2023-05-29",
    "individual_predictions": {
      "cf_glm_model": 0.513,
      "cf_lda_model": 0.928,
      "cf_nn_model": 0.554,
      "cf_nn_nn_model": 0.251,
      "cf_rf_model": 0.677,
      "cf_svm_model": 0.837,
      "cg_glm_model": 0.573,
      "cg_lda_model": 0.706,
      "cg_nn_model": 0.729,
      "cg_rf_model": 0.383,
      "cg_svm_model": 0.506
    },
    "ensemble": {
      "cf": 0.6267896983225834,
      "cg": 0.579183248834594,
      "overall": 0.6051818181818182
    },
    "features": {
      "latitude": 22.75,
      "longitude": 120.25
    }
  },
  {
    "date": "2023-05-29",
    "individual_predictions": {
      "cf_glm_model": 0.511,
      "cf_lda_model": 0.93,
      "cf_nn_model": 0.364,
      "cf_nn_nn_model": 0.155,
      "cf_rf_model": 0.805,
      "cf_svm_model": 0.833,
      "cg_glm_model": 0.601,
      "cg_lda_model": 0.754,
      "cg_nn_model": 0.729,
      "cg_rf_model": 0.368,
      "cg_svm_model": 0.488
    },
    "ensemble": {
      "cf": 0.5997067584692705,
      "cg": 0.5879268125162675,
      "overall": 0.5943636363636364
    },
    "features": {
      "latitude": 23.0,
      "longitude": 120.25
    }
  },
  {
    "date": "2023-05-29",
    "individual_predictions": {
      "cf_glm_model": 0.51,
      "cf_lda_model": 0.937,
      "cf_nn_model": 0.364,
      "cf_nn_nn_model": 0.155,
      "cf_rf_model": 0.88,
      "cf_svm_model": 0.829,
      "cg_glm_model": 0.626,
      "cg_lda_model": 0.686,
      "cg_nn_model": 0.729,
      "cg_rf_model": 0.338,
      "cg_svm_model": 0.473
    },
    "ensemble": {
      "cf": 0.6122886482133639,
      "cg": 0.5701811793799746,
      "overall": 0.5933636363636364
    },
    "features": {
      "latitude": 23.25,
      "longitude": 120.25
    }
  },
  {
    "date": "2023-05-29",
    "individual_predictions": {
      "cf_glm_model": 0.511,
      "cf_lda_model": 0.928,
      "cf_nn_model": 0.364,
      "cf_nn_nn_model": 0.155,
      "cf_rf_model": 0.875,
      "cf_svm_model": 0.83,
      "cg_glm_model": 0.622,
      "cg_lda_model": 0.737,
      "cg_nn_model": 0.729,
      "cg_rf_model": 0.375,
      "cg_svm_model": 0.476
    },
    "ensemble": {
      "cf": 0.6102704263103984,
      "cg": 0.5875750498540934,
      "overall": 0.6001818181818183
    },
    "features": {
      "latitude": 23.5,
      "longitude": 120.25
    }
  },
  {
    "date": "2023-05-29",
    "individual_predictions": {
      "cf_glm_model": 0.512,
      "cf_lda_model": 0.904,
      "cf_nn_model": 0.364,
      "cf_nn_nn_model": 0.155,
      "cf_rf_model": 0.853,
      "cf_svm_model": 0.832,
      "cg_glm_model": 0.608,
      "cg_lda_model": 0.981,
      "cg_nn_model": 0.729,
      "cg_rf_model": 0.508,
      "cg_svm_model": 0.485
    },
    "ensemble": {
      "cf": 0.6032456851760574,
      "cg": 0.6622099732737606,
      "overall": 0.6300909090909091
    },
    "features": {
      "latitude": 23.75,
      "longitude": 120.25
    }
  },
  {
    "date": "2023-05-29",
    "individual_predictions": {
      "cf_glm_model": 0.513,
      "cf_lda_model": 0.913,
      "cf_nn_model": 0.364,
      "cf_nn_nn_model": 0.155,
      "cf_rf_model": 0.841,
      "cf_svm_model": 0.832,
      "cg_glm_model": 0.608,
      "cg_lda_model": 0.979,
      "cg_nn_model": 0.729,
      "cg_rf_model": 0.528,
      "cg_svm_model": 0.485
    },
    "ensemble": {
      "cf": 0.602868221080774,
      "cg": 0.6657652677000861,
      "overall": 0.6315454545454545
    },
    "features": {
      "latitude": 24.0,
      "longitude": 120.25
    }
  },
  {
    "date": "2023-05-29",
    "individual_predictions": {
      "cf_glm_model": 0.516,
      "cf_lda_model": 0.943,
      "cf_nn_model": 0.364,
      "cf_nn_nn_model": 0.155,
      "cf_rf_model": 0.82,
      "cf_svm_model": 0.837,
      "cg_glm_model": 0.579,
      "cg_lda_model": 0.979,
      "cg_nn_model": 0.729,
      "cg_rf_model": 0.535,
      "cg_svm_model": 0.5
    },
    "ensemble": {
      "cf": 0.6057164105869253,
      "cg": 0.6642314666346953,
      "overall": 0.6324545454545455
    },
    "features": {
      "latitude": 24.25,
      "longitude": 120.25
    }
  },
  {
    "date": "2023-05-29",
    "individual_predictions": {
      "cf_glm_model": 0.509,
      "cf_lda_model": 0.961,
      "cf_nn_model": 0.364,
      "cf_nn_nn_model": 0.155,
      "cf_rf_model": 0.739,
      "cf_svm_model": 0.833,
      "cg_glm_model": 0.6,
      "cg_lda_model": 0.961,
      "cg_nn_model": 0.729,
      "cg_rf_model": 0.47,
      "cg_svm_model": 0.487
    },
    "ensemble": {
      "cf": 0.5933882404425622,
      "cg": 0.6493271466714701,
      "overall": 0.6189090909090909
    },
    "features": {
      "latitude": 21.75,
      "longitude": 120.5
    }
  },
  {
    "date": "2023-05-29",
    "individual_predictions": {
      "cf_glm_model": 0.511,
      "cf_lda_model": 0.948,
      "cf_nn_model": 0.364,
      "cf_nn_nn_model": 0.155,
      "cf_rf_model": 0.765,
      "cf_svm_model": 0.835,
      "cg_glm_model": 0.586,
      "cg_lda_model": 0.92,
      "cg_nn_model": 0.729,
      "cg_rf_model": 0.49,
      "cg_svm_model": 0.5
    },
    "ensemble": {
      "cf": 0.596134595348432,
      "cg": 0.6450193612532603,
      "overall": 0.6184545454545455
    },
    "features": {
      "latitude": 22.0,
      "longitude": 120.5
    }
  },
  {
    "date": "2023-05-29",
    "individual_predictions": {
      "cf_glm_model": 0.512,
      "cf_lda_model": 0.909,
      "cf_nn_model": 0.364,
      "cf_nn_nn_model": 0.155,
      "cf_rf_model": 0.668,
      "cf_svm_model": 0.836,
      "cg_glm_model": 0.579,
      "cg_lda_model": 0.899,
      "cg_nn_model": 0.729,
      "cg_rf_model": 0.505,
      "cg_svm_model": 0.5
    },
    "ensemble": {
      "cf": 0.5738721225670402,
      "cg": 0.6422484158097529,
      "overall": 0.6050909090909091
    },
    "features": {
      "latitude": 22.25,
      "longitude": 120.5
    }
  },
  {
    "date": "2023-05-29",
    "individual_predictions": {
      "cf_glm_model": 0.513,
      "cf_lda_model": 0.895,
      "cf_nn_model": 0.554,
      "cf_nn_nn_model": 0.251,
      "cf_rf_model": 0.744,
      "cf_svm_model": 0.837,
      "cg_glm_model": 0.572,
      "cg_lda_model": 0.798,
      "cg_nn_model": 0.729,
      "cg_rf_model": 0.44,
      "cg_svm_model": 0.505
    },
    "ensemble": {
      "cf": 0.632259785046264,
      "cg": 0.6088440902293862,
      "overall": 0.6216363636363637
    },
    "features": {
      "latitude": 22.5,
      "longitude": 120.5
    }
  },
  {
    "date": "2023-05-29",
    "individual_predictions": {
      "cf_glm_model": 0.514,
      "cf_lda_model": 0.888,
      "cf_nn_model": 0.554,
      "cf_nn_nn_model": 0.251,
      "cf_rf_model": 0.873,
      "cf_svm_model": 0.837,
      "cg_glm_model": 0.573,
      "cg_lda_model": 0.784,
      "cg_nn_model": 0.729,
      "cg_rf_model": 0.534,
      "cg_svm_model": 0.506
    },
    "ensemble": {
      "cf": 0.6527305813552537,
      "cg": 0.6251241246068723,
      "overall": 0.6402727272727273
    },
    "features": {
      "latitude": 22.75,
      "longitude": 120.5
    }
  },
  {
    "date": "2023-05-29",
    "individual_predictions": {
      "cf_glm_model": 0.515,
      "cf_lda_model": 0.869,
      "cf_nn_model": 0.554,
      "cf_nn_nn_model": 0.251,
      "cf_rf_model": 0.901,
      "cf_svm_model": 0.84,
      "cg_glm_model": 0.554,
      "cg_lda_model": 0.828,
      "cg_nn_model": 0.729,
      "cg_rf_model": 0.568,
      "cg_svm_model": 0.517
    },
    "ensemble": {
      "cf": 0.6549245204161175,
      "cg": 0.639145486324449,
      "overall": 0.6478181818181818
    },
    "features": {
      "latitude": 23.0,
      "longitude": 120.5
    }
  },
  {
    "date": "2023-05-29",
    "individual_predictions": {
      "cf_glm_model": 0.511,
      "cf_lda_model": 0.957,
      "cf_nn_model": 0.364,
      "cf_nn_nn_model": 0.155,
      "cf_rf_model": 0.889,
      "cf_svm_model": 0.831,
      "cg_glm_model": 0.616,
      "cg_lda_model": 0.532,
      "cg_nn_model": 0.729,
      "cg_rf_model": 0.468,
      "cg_svm_model": 0.479
    },
    "ensemble": {
      "cf": 0.6175634396754053,
      "cg": 0.5647075257941391,
      "overall": 0.5937272727272728
    },
    "features": {
      "latitude": 23.25,
      "longitude": 120.5
    }
  },
  {
    "date": "2023-05-29",
    "individual_predictions": {
      "cf_glm_model": 0.512,
      "cf_lda_model": 0.897,
      "cf_nn_model": 0.364,
      "cf_nn_nn_model": 0.155,
      "cf_rf_model": 0.859,
      "cf_svm_model": 0.832,
      "cg_glm_model": 0.608,
      "cg_lda_model": 0.961,
      "cg_nn_model": 0.729,
      "cg_rf_model": 0.493,
      "cg_svm_model": 0.485
    },
    "ensemble": {
      "cf": 0.6030572407488197,
      "cg": 0.655054594802994,
      "overall": 0.6268181818181818
    },
    "features": {
      "latitude": 23.5,
      "longitude": 120.5
    }
  },
  {
    "date": "2023-05-29",
    "individual_predictions": {
      "cf_glm_model": 0.512,
      "cf_lda_model": 0.936,
      "cf_nn_model": 0.364,
      "cf_nn_nn_model": 0.155,
      "cf_rf_model": 0.871,
      "cf_svm_model": 0.831,
      "cg_glm_model": 0.612,
      "cg_lda_model": 0.761,
      "cg_nn_model": 0.729,
      "cg_rf_model": 0.455,
      "cg_svm_model": 0.483
    },
    "ensemble": {
      "cf": 0.6114382253069692,
      "cg": 0.6078422894954458,
      "overall": 0.6099090909090908
    },
    "features": {
      "latitude": 23.75,
      "longitude": 120.5
    }
  },
  {
    "date": "2023-05-29",
    "individual_predictions": {
      "cf_glm_model": 0.515,
      "cf_lda_model": 0.916,
      "cf_nn_model": 0.364,
      "cf_nn_nn_model": 0.155,
      "cf_rf_model": 0.885,
      "cf_svm_model": 0.837,
      "cg_glm_model": 0.579,
      "cg_lda_model": 0.965,
      "cg_nn_model": 0.729,
      "cg_rf_model": 0.55,
      "cg_svm_model": 0.5
    },
    "ensemble": {
      "cf": 0.6118512964714796,
      "cg": 0.6644516464751012,
      "overall": 0.6359090909090909
    },
    "features": {
      "latitude": 24.0,
      "longitude": 120.5
    }
  },
  {
    "date": "2023-05-29",
    "individual_predictions": {
      "cf_glm_model": 0.519,
      "cf_lda_model": 0.854,
      "cf_nn_model": 0.554,
      "cf_nn_nn_model": 0.251,
      "cf_rf_model": 0.846,
      "cf_svm_model": 0.842,
      "cg_glm_model": 0.54,
      "cg_lda_model": 0.996,
      "cg_nn_model": 0.556,
      "cg_rf_model": 0.638,
      "cg_svm_model": 0.527
    },
    "ensemble": {
      "cf": 0.6442896447386705,
      "cg": 0.6516155123340948,
      "overall": 0.6475454545454545
    },
    "features": {
      "latitude": 24.25,
      "longitude": 120.5
    }
  },
  {
    "date": "2023-05-29",
    "individual_predictions": {
      "cf_glm_model": 0.519,
      "cf_lda_model": 0.851,
      "cf_nn_model": 0.554,
      "cf_nn_nn_model": 0.251,
      "cf_rf_model": 0.849,
      "cf_svm_model": 0.842,
      "cg_glm_model": 0.54,
      "cg_lda_model": 0.998,
      "cg_nn_model": 0.556,
      "cg_rf_model": 0.638,
      "cg_svm_model": 0.528
    },
    "ensemble": {
      "cf": 0.6443996266080366,
      "cg": 0.6520154178329627,
      "overall": 0.6478181818181817
    },
    "features": {
      "latitude": 24.5,
      "longitude": 120.5
    }
  },
  {
    "date": "2023-05-29",
    "individual_predictions": {
      "cf_glm_model": 0.509,
      "cf_lda_model": 0.959,
      "cf_nn_model": 0.364,
      "cf_nn_nn_model": 0.155,
      "cf_rf_model": 0.75,
      "cf_svm_model": 0.831,
      "cg_glm_model": 0.609,
      "cg_lda_model": 0.988,
      "cg_nn_model": 0.729,
      "cg_rf_model": 0.495,
      "cg_svm_model": 0.481
    },
    "ensemble": {
      "cf": 0.5944513467192171,
      "cg": 0.6604552275473934,
      "overall": 0.6245454545454545
    },
    "features": {
      "latitude": 21.75,
      "longitude": 120.75
    }
  },
  {
    "date": "2023-05-29",
    "individual_predictions": {
      "cf_glm_model": 0.51,
      "cf_lda_model": 0.949,
      "cf_nn_model": 0.364,
      "cf_nn_nn_model": 0.155,
      "cf_rf_model": 0.729,
      "cf_svm_model": 0.833,
      "cg_glm_model": 0.596,
      "cg_lda_model": 0.986,
      "cg_nn_model": 0.729,
      "cg_rf_model": 0.485,
      "cg_svm_model": 0.49
    },
    "ensemble": {
      "cf": 0.5898595711982076,
      "cg": 0.6569849311919357,
      "overall": 0.6205454545454546
    },
    "features": {
      "latitude": 22.0,
      "longitude": 120.75
    }
  },
  {
    "date": "2023-05-29",
    "individual_predictions": {
      "cf_glm_model": 0.516,
      "cf_lda_model": 0.974,
      "cf_nn_model": 0.554,
      "cf_nn_nn_model": 0.251,
      "cf_rf_model": 0.921,
      "cf_svm_model": 0.842,
      "cg_glm_model": 0.538,
      "cg_lda_model": 0.965,
      "cg_nn_model": 0.556,
      "cg_rf_model": 0.674,
      "cg_svm_model": 0.526
    },
    "ensemble": {
      "cf": 0.6762490135776815,
      "cg": 0.6517912797520469,
      "overall": 0.6651818181818182
    },
    "features": {
      "latitude": 22.25,
      "longitude": 120.75
    }
  },
  {
    "date": "2023-05-29",
    "individual_predictions": {
      "cf_glm_model": 0.528,
      "cf_lda_model": 0.992,
      "cf_nn_model": 0.77,
      "cf_nn_nn_model": 0.31,
      "cf_rf_model": 0.84,
      "cf_svm_model": 0.857,
      "cg_glm_model": 0.404,
      "cg_lda_model": 0.304,
      "cg_nn_model": 0.352,
      "cg_rf_model": 0.555,
      "cg_svm_model": 0.599
    },
    "ensemble": {
      "cf": 0.7159290285547439,
      "cg": 0.4426747921682221,
      "overall": 0.591909090909091
    },
    "features": {
      "latitude": 22.5,
      "longitude": 120.75
    }
  },
  {
    "date": "2023-05-29",
    "individual_predictions": {
      "cf_glm_model": 0.52,
      "cf_lda_model": 0.967,
      "cf_nn_model": 0.554,
      "cf_nn_nn_model": 0.251,
      "cf_rf_model": 0.876,
      "cf_svm_model": 0.846,
      "cg_glm_model": 0.502,
      "cg_lda_model": 0.756,
      "cg_nn_model": 0.556,
      "cg_rf_model": 0.639,
      "cg_svm_model": 0.547
    },
    "ensemble": {
      "cf": 0.6690068890332518,
      "cg": 0.59995113185778,
      "overall": 0.6376363636363637
    },
    "features": {
      "latitude": 22.75,
      "longitude": 120.75
    }
  },
  {
    "date": "2023-05-29",
    "individual_predictions": {
      "cf_glm_model": 0.528,
      "cf_lda_model": 0.988,
      "cf_nn_model": 0.77,
      "cf_nn_nn_model": 0.31,
      "cf_rf_model": 0.865,
      "cf_svm_model": 0.857,
      "cg_glm_model": 0.405,
      "cg_lda_model": 0.244,
      "cg_nn_model": 0.352,
      "cg_rf_model": 0.635,
      "cg_svm_model": 0.599
    },
    "ensemble": {
      "cf": 0.7196589217388546,
      "cg": 0.4467456916035548,
      "overall": 0.5957272727272728
    },
    "features": {
      "latitude": 23.0,
      "longitude": 120.75
    }
  },
  {
    "date": "2023-05-29",
    "individual_predictions": {
      "cf_glm_model": 0.517,
      "cf_lda_model": 0.995,
      "cf_nn_model": 0.554,
      "cf_nn_nn_model": 0.251,
      "cf_rf_model": 0.374,
      "cf_svm_model": 0.841,
      "cg_glm_model": 0.543,
      "cg_lda_model": 0.048,
      "cg_nn_model": 0.729,
      "cg_rf_model": 0.495,
      "cg_svm_model": 0.524
    },
    "ensemble": {
      "cf": 0.5886624143351505,
      "cg": 0.4677210367878043,
      "overall": 0.5337272727272727
    },
    "features": {
      "latitude": 23.25,
      "longitude": 120.75
    }
  },
  {
    "date": "2023-05-29",
    "individual_predictions": {
      "cf_glm_model": 0.514,
      "cf_lda_model": 0.983,
      "cf_nn_model": 0.364,
      "cf_nn_nn_model": 0.155,
      "cf_rf_model": 0.819,
      "cf_svm_model": 0.835,
      "cg_glm_model": 0.589,
      "cg_lda_model": 0.327,
      "cg_nn_model": 0.729,
      "cg_rf_model": 0.415,
      "cg_svm_model": 0.5
    },
    "ensemble": {
      "cf": 0.611594978620532,
      "cg": 0.5118080088817696,
      "overall": 0.5663636363636364
    },
    "features": {
      "latitude": 23.5,
      "longitude": 120.75
    }
  },
  {
    "date": "2023-05-29",
    "individual_predictions": {
      "cf_glm_model": 0.517,
      "cf_lda_model": 0.957,
      "cf_nn_model": 0.554,
      "cf_nn_nn_model": 0.251,
      "cf_rf_model": 0.937,
      "cf_svm_model": 0.839,
      "cg_glm_model": 0.559,
      "cg_lda_model": 0.891,
      "cg_nn_model": 0.729,
      "cg_rf_model": 0.61,
      "cg_svm_model": 0.515
    },
    "ensemble": {
      "cf": 0.6757354148355179,
      "cg": 0.6607816827582947,
      "overall": 0.669
    },
    "features": {
      "latitude": 23.75,
      "longitude": 120.75
    }
  },
  {
    "date": "2023-05-29",
    "individual_predictions": {
      "cf_glm_model": 0.517,
      "cf_lda_model": 0.944,
      "cf_nn_model": 0.554,
      "cf_nn_nn_model": 0.251,
      "cf_rf_model": 0.933,
      "cf_svm_model": 0.839,
      "cg_glm_model": 0.559,
      "cg_lda_model": 0.911,
      "cg_nn_model": 0.729,
      "cg_rf_model": 0.605,
      "cg_svm_model": 0.516
    },
    "ensemble": {
      "cf": 0.6728892588848825,
      "cg": 0.6639606097516355,
      "overall": 0.668909090909091
    },
    "features": {
      "latitude": 24.0,
      "longitude": 120.75
    }
  },
  {
    "date": "2023-05-29",
    "individual_predictions": {
      "cf_glm_model": 0.517,
      "cf_lda_model": 0.938,
      "cf_nn_model": 0.554,
      "cf_nn_nn_model": 0.251,
      "cf_rf_model": 0.935,
      "cf_svm_model": 0.839,
      "cg_glm_model": 0.56,
      "cg_lda_model": 0.91,
      "cg_nn_model": 0.729,
      "cg_rf_model": 0.605,
      "cg_svm_model": 0.516
    },
    "ensemble": {
      "cf": 0.6723649661111204,
      "cg": 0.6637804293896465,
      "overall": 0.6685454545454547
    },
    "features": {
      "latitude": 24.25,
      "longitude": 120.75
    }
  },
  {
    "date": "2023-05-29",
    "individual_predictions": {
      "cf_glm_model": 0.521,
      "cf_lda_model": 0.883,
      "cf_nn_model": 0.554,
      "cf_nn_nn_model": 0.251,
      "cf_rf_model": 0.933,
      "cf_svm_model": 0.844,
      "cg_glm_model": 0.521,
      "cg_lda_model": 0.998,
      "cg_nn_model": 0.556,
      "cg_rf_model": 0.739,
      "cg_svm_model": 0.539
    },
    "ensemble": {
      "cf": 0.6642846734775137,
      "cg": 0.6705358823177502,
      "overall": 0.6671818181818182
    },
    "features": {
      "latitude": 24.5,
      "longitude": 120.75
    }
  },
  {
    "date": "2023-05-29",
    "individual_predictions": {
      "cf_glm_model": 0.521,
      "cf_lda_model": 0.875,
      "cf_nn_model": 0.554,
      "cf_nn_nn_model": 0.251,
      "cf_rf_model": 0.872,
      "cf_svm_model": 0.844,
      "cg_glm_model": 0.521,
      "cg_lda_model": 0.999,
      "cg_nn_model": 0.556,
      "cg_rf_model": 0.72,
      "cg_svm_model": 0.539
    },
    "ensemble": {
      "cf": 0.6529552827276998,
      "cg": 0.6669497992887513,
      "overall": 0.6592727272727271
    },
    "features": {
      "latitude": 24.75,
      "longitude": 120.75
    }
  },
  {
    "date": "2023-05-29",
    "individual_predictions": {
      "cf_glm_model": 0.509,
      "cf_lda_model": 0.931,
      "cf_nn_model": 0.364,
      "cf_nn_nn_model": 0.155,
      "cf_rf_model": 0.758,
      "cf_svm_model": 0.832,
      "cg_glm_model": 0.601,
      "cg_lda_model": 0.993,
      "cg_nn_model": 0.729,
      "cg_rf_model": 0.545,
      "cg_svm_model": 0.487
    },
    "ensemble": {
      "cf": 0.5916195640215987,
      "cg": 0.6707247752499166,
      "overall": 0.6276363636363637
    },
    "features": {
      "latitude": 21.75,
      "longitude": 121.0
    }
  },
  {
    "date": "2023-05-29",
    "individual_predictions": {
      "cf_glm_model": 0.511,
      "cf_lda_model": 0.896,
      "cf_nn_model": 0.364,
      "cf_nn_nn_model": 0.155,
      "cf_rf_model": 0.746,
      "cf_svm_model": 0.835,
      "cg_glm_model": 0.584,
      "cg_lda_model": 0.998,
      "cg_nn_model": 0.729,
      "cg_rf_model": 0.56,
      "cg_svm_model": 0.5
    },
    "ensemble": {
      "cf": 0.5845120111198567,
      "cg": 0.6741762274463725,
      "overall": 0.6252727272727273
    },
    "features": {
      "latitude": 22.0,
      "longitude": 121.0
    }
  },
  {
    "date": "2023-05-29",
    "individual_predictions": {
      "cf_glm_model": 0.518,
      "cf_lda_model": 0.946,
      "cf_nn_model": 0.554,
      "cf_nn_nn_model": 0.251,
      "cf_rf_model": 0.59,
      "cf_svm_model": 0.845,
      "cg_glm_model": 0.509,
      "cg_lda_model": 0.989,
      "cg_nn_model": 0.556,
      "cg_rf_model": 0.665,
      "cg_svm_model": 0.542
    },
    "ensemble": {
      "cf": 0.6173242697188431,
      "cg": 0.6522547849164917,
      "overall": 0.6331818181818182
    },
    "features": {
      "latitude": 22.25,
      "longitude": 121.0
    }
  },
  {
    "date": "2023-05-29",
    "individual_predictions": {
      "cf_glm_model": 0.518,
      "cf_lda_model": 0.96,
      "cf_nn_model": 0.554,
      "cf_nn_nn_model": 0.251,
      "cf_rf_model": 0.656,
      "cf_svm_model": 0.845,
      "cg_glm_model": 0.509,
      "cg_lda_model": 0.968,
      "cg_nn_model": 0.556,
      "cg_rf_model": 0.705,
      "cg_svm_model": 0.542
    },
    "ensemble": {
      "cf": 0.6308195144613857,
      "cg": 0.6562501072063829,
      "overall": 0.6421818181818181
    },
    "features": {
      "latitude": 22.5,
      "longitude": 121.0
    }
  },
  {
    "date": "2023-05-29",
    "individual_predictions": {
      "cf_glm_model": 0.52,
      "cf_lda_model": 0.953,
      "cf_nn_model": 0.554,
      "cf_nn_nn_model": 0.251,
      "cf_rf_model": 0.902,
      "cf_svm_model": 0.846,
      "cg_glm_model": 0.503,
      "cg_lda_model": 0.862,
      "cg_nn_model": 0.556,
      "cg_rf_model": 0.619,
      "cg_svm_model": 0.546
    },
    "ensemble": {
      "cf": 0.6709575385517151,
      "cg": 0.6172274577912941,
      "overall": 0.6465454545454545
    },
    "features": {
      "latitude": 22.75,
      "longitude": 121.0
    }
  },
  {
    "date": "2023-05-29",
    "individual_predictions": {
      "cf_glm_model": 0.519,
      "cf_lda_model": 0.995,
      "cf_nn_model": 0.554,
      "cf_nn_nn_model": 0.251,
      "cf_rf_model": 0.334,
      "cf_svm_model": 0.844,
      "cg_glm_model": 0.52,
      "cg_lda_model": 0.006,
      "cg_nn_model": 0.556,
      "cg_rf_model": 0.515,
      "cg_svm_model": 0.537
    },
    "ensemble": {
      "cf": 0.5828080282676813,
      "cg": 0.42703442905304323,
      "overall": 0.5119090909090909
    },
    "features": {
      "latitude": 23.0,
      "longitude": 121.0
    }
  },
  {
    "date": "2023-05-29",
    "individual_predictions": {
      "cf_glm_model": 0.518,
      "cf_lda_model": 0.997,
      "cf_nn_model": 0.554,
      "cf_nn_nn_model": 0.251,
      "cf_rf_model": 0.369,
      "cf_svm_model": 0.841,
      "cg_glm_model": 0.543,
      "cg_lda_model": 0.01,
      "cg_nn_model": 0.729,
      "cg_rf_model": 0.535,
      "cg_svm_model": 0.524
    },
    "ensemble": {
      "cf": 0.5884032678268216,
      "cg": 0.4682492380427276,
      "overall": 0.5337272727272727
    },
    "features": {
      "latitude": 23.25,
      "longitude": 121.0
    }
  },
  {
    "date": "2023-05-29",
    "individual_predictions": {
      "cf_glm_model": 0.518,
      "cf_lda_model": 0.997,
      "cf_nn_model": 0.554,
      "cf_nn_nn_model": 0.251,
      "cf_rf_model": 0.369,
      "cf_svm_model": 0.841,
      "cg_glm_model": 0.544,
      "cg_lda_model": 0.006,
      "cg_nn_model": 0.729,
      "cg_rf_model": 0.56,
      "cg_svm_model": 0.524
    },
    "ensemble": {
      "cf": 0.5884284616246046,
      "cg": 0.4724972742473632,
      "overall": 0.5357272727272727
    },
    "features": {
      "latitude": 23.5,
      "longitude": 121.0
    }
  },
  {
    "date": "2023-05-29",
    "individual_predictions": {
      "cf_glm_model": 0.518,
      "cf_lda_model": 0.996,
      "cf_nn_model": 0.554,
      "cf_nn_nn_model": 0.251,
      "cf_rf_model": 0.329,
      "cf_svm_model": 0.841,
      "cg_glm_model": 0.544,
      "cg_lda_model": 0.024,
      "cg_nn_model": 0.729,
      "cg_rf_model": 0.49,
      "cg_svm_model": 0.524
    },
    "ensemble": {
      "cf": 0.5816223998886656,
      "cg": 0.4621523937140316,
      "overall": 0.5272727272727273
    },
    "features": {
      "latitude": 23.75,
      "longitude": 121.0
    }
  },
  {
    "date": "2023-05-29",
    "individual_predictions": {
      "cf_glm_model": 0.52,
      "cf_lda_model": 0.983,
      "cf_nn_model": 0.554,
      "cf_nn_nn_model": 0.251,
      "cf_rf_model": 0.904,
      "cf_svm_model": 0.844,
      "cg_glm_model": 0.521,
      "cg_lda_model": 0.845,
      "cg_nn_model": 0.556,
      "cg_rf_model": 0.589,
      "cg_svm_model": 0.538
    },
    "ensemble": {
      "cf": 0.6760918930489849,
      "cg": 0.6097764129379379,
      "overall": 0.645909090909091
    },
    "features": {
      "latitude": 24.0,
      "longitude": 121.0
    }
  },
  {
    "date": "2023-05-29",
    "individual_predictions": {
      "cf_glm_model": 0.532,
      "cf_lda_model": 0.997,
      "cf_nn_model": 0.443,
      "cf_nn_nn_model": 0.152,
      "cf_rf_model": 0.482,
      "cf_svm_model": 0.858,
      "cg_glm_model": 0.39,
      "cg_lda_model": 0.507,
      "cg_nn_model": 0.352,
      "cg_rf_model": 0.52,
      "cg_svm_model": 0.608
    },
    "ensemble": {
      "cf": 0.5773102535094675,
      "cg": 0.4754015260944011,
      "overall": 0.531
    },
    "features": {
      "latitude": 24.25,
      "longitude": 121.0
    }
  },
  {
    "date": "2023-05-29",
    "individual_predictions": {
      "cf_glm_model": 0.534,
      "cf_lda_model": 0.997,
      "cf_nn_model": 0.443,
      "cf_nn_nn_model": 0.152,
      "cf_rf_model": 0.327,
      "cf_svm_model": 0.86,
      "cg_glm_model": 0.371,
      "cg_lda_model": 0.585,
      "cg_nn_model": 0.409,
      "cg_rf_model": 0.535,
      "cg_svm_model": 0.618
    },
    "ensemble": {
      "cf": 0.5521695743429418,
      "cg": 0.5036000728969346,
      "overall": 0.5300909090909092
    },
    "features": {
      "latitude": 24.5,
      "longitude": 121.0
    }
  },
  {
    "date": "2023-05-29",
    "individual_predictions": {
      "cf_glm_model": 0.548,
      "cf_lda_model": 0.915,
      "cf_nn_model": 0.297,
      "cf_nn_nn_model": 0.102,
      "cf_rf_model": 0.924,
      "cf_svm_model": 0.871,
      "cg_glm_model": 0.236,
      "cg_lda_model": 0.997,
      "cg_nn_model": 0.468,
      "cg_rf_model": 0.719,
      "cg_svm_model": 0.678
    },
    "ensemble": {
      "cf": 0.609585112204124,
      "cg": 0.6194711648088231,
      "overall": 0.6140909090909091
    },
    "features": {
      "latitude": 24.75,
      "longitude": 121.0
    }
  },
  {
    "date": "2023-05-29",
    "individual_predictions": {
      "cf_glm_model": 0.548,
      "cf_lda_model": 0.947,
      "cf_nn_model": 0.297,
      "cf_nn_nn_model": 0.102,
      "cf_rf_model": 0.79,
      "cf_svm_model": 0.871,
      "cg_glm_model": 0.236,
      "cg_lda_model": 0.996,
      "cg_nn_model": 0.468,
      "cg_rf_model": 0.635,
      "cg_svm_model": 0.678
    },
    "ensemble": {
      "cf": 0.5923075199835639,
      "cg": 0.6024906051510007,
      "overall": 0.597090909090909
    },
    "features": {
      "latitude": 25.0,
      "longitude": 121.0
    }
  },
  {
    "date": "2023-05-29",
    "individual_predictions": {
      "cf_glm_model": 0.511,
      "cf_lda_model": 0.92,
      "cf_nn_model": 0.364,
      "cf_nn_nn_model": 0.155,
      "cf_rf_model": 0.709,
      "cf_svm_model": 0.835,
      "cg_glm_model": 0.585,
      "cg_lda_model": 0.985,
      "cg_nn_model": 0.729,
      "cg_rf_model": 0.515,
      "cg_svm_model": 0.5
    },
    "ensemble": {
      "cf": 0.5821353829359909,
      "cg": 0.6627786991903754,
      "overall": 0.6189090909090909
    },
    "features": {
      "latitude": 21.75,
      "longitude": 121.25
    }
  },
  {
    "date": "2023-05-29",
    "individual_predictions": {
      "cf_glm_model": 0.512,
      "cf_lda_model": 0.934,
      "cf_nn_model": 0.554,
      "cf_nn_nn_model": 0.251,
      "cf_rf_model": 0.694,
      "cf_svm_model": 0.837,
      "cg_glm_model": 0.57,
      "cg_lda_model": 0.995,
      "cg_nn_model": 0.729,
      "cg_rf_model": 0.57,
      "cg_svm_model": 0.506
    },
    "ensemble": {
      "cf": 0.6303868069035689,
      "cg": 0.6738362196128046,
      "overall": 0.6501818181818183
    },
    "features": {
      "latitude": 22.0,
      "longitude": 121.25
    }
  },
  {
    "date": "2023-05-29",
    "individual_predictions": {
      "cf_glm_model": 0.518,
      "cf_lda_model": 0.943,
      "cf_nn_model": 0.554,
      "cf_nn_nn_model": 0.251,
      "cf_rf_model": 0.595,
      "cf_svm_model": 0.845,
      "cg_glm_model": 0.509,
      "cg_lda_model": 0.989,
      "cg_nn_model": 0.556,
      "cg_rf_model": 0.665,
      "cg_svm_model": 0.542
    },
    "ensemble": {
      "cf": 0.6175381380337456,
      "cg": 0.6522694958771645,
      "overall": 0.6333636363636364
    },
    "features": {
      "latitude": 22.25,
      "longitude": 121.25
    }
  },
  {
    "date": "2023-05-29",
    "individual_predictions": {
      "cf_glm_model": 0.518,
      "cf_lda_model": 0.947,
      "cf_nn_model": 0.554,
      "cf_nn_nn_model": 0.251,
      "cf_rf_model": 0.595,
      "cf_svm_model": 0.845,
      "cg_glm_model": 0.51,
      "cg_lda_model": 0.988,
      "cg_nn_model": 0.556,
      "cg_rf_model": 0.66,
      "cg_svm_model": 0.542
    },
    "ensemble": {
      "cf": 0.6183570367271761,
      "cg": 0.6511854366610695,
      "overall": 0.6332727272727273
    },
    "features": {
      "latitude": 22.5,
      "longitude": 121.25
    }
  },
  {
    "date": "2023-05-29",
    "individual_predictions": {
      "cf_glm_model": 0.519,
      "cf_lda_model": 0.914,
      "cf_nn_model": 0.554,
      "cf_nn_nn_model": 0.251,
      "cf_rf_model": 0.801,
      "cf_svm_model": 0.845,
      "cg_glm_model": 0.511,
      "cg_lda_model": 0.997,
      "cg_nn_model": 0.556,
      "cg_rf_model": 0.67,
      "cg_svm_model": 0.542
    },
    "ensemble": {
      "cf": 0.6473550596801636,
      "cg": 0.6552782142074347,
      "overall": 0.6509090909090909
    },
    "features": {
      "latitude": 22.75,
      "longitude": 121.25
    }
  },
  {
    "date": "2023-05-29",
    "individual_predictions": {
      "cf_glm_model": 0.531,
      "cf_lda_model": 0.907,
      "cf_nn_model": 0.443,
      "cf_nn_nn_model": 0.152,
      "cf_rf_model": 0.759,
      "cf_svm_model": 0.86,
      "cg_glm_model": 0.368,
      "cg_lda_model": 0.892,
      "cg_nn_model": 0.409,
      "cg_rf_model": 0.635,
      "cg_svm_model": 0.617
    },
    "ensemble": {
      "cf": 0.6086606940742197,
      "cg": 0.584242806806859,
      "overall": 0.5975454545454546
    },
    "features": {
      "latitude": 23.0,
      "longitude": 121.25
    }
  },
  {
    "date": "2023-05-29",
    "individual_predictions": {
      "cf_glm_model": 0.531,
      "cf_lda_model": 0.975,
      "cf_nn_model": 0.443,
      "cf_nn_nn_model": 0.152,
      "cf_rf_model": 0.78,
      "cf_svm_model": 0.859,
      "cg_glm_model": 0.375,
      "cg_lda_model": 0.2,
      "cg_nn_model": 0.352,
      "cg_rf_model": 0.659,
      "cg_svm_model": 0.614
    },
    "ensemble": {
      "cf": 0.6234859116729409,
      "cg": 0.4398040825063444,
      "overall": 0.5399999999999999
    },
    "features": {
      "latitude": 23.25,
      "longitude": 121.25
    }
  },
  {
    "date": "2023-05-29",
    "individual_predictions": {
      "cf_glm_model": 0.531,
      "cf_lda_model": 0.976,
      "cf_nn_model": 0.443,
      "cf_nn_nn_model": 0.152,
      "cf_rf_model": 0.784,
      "cf_svm_model": 0.859,
      "cg_glm_model": 0.376,
      "cg_lda_model": 0.305,
      "cg_nn_model": 0.352,
      "cg_rf_model": 0.679,
      "cg_svm_model": 0.614
    },
    "ensemble": {
      "cf": 0.6241674158109976,
      "cg": 0.4651070561063772,
      "overall": 0.551909090909091
    },
    "features": {
      "latitude": 23.5,
      "longitude": 121.25
    }
  },
  {
    "date": "2023-05-29",
    "individual_predictions": {
      "cf_glm_model": 0.518,
      "cf_lda_model": 0.995,
      "cf_nn_model": 0.554,
      "cf_nn_nn_model": 0.251,
      "cf_rf_model": 0.384,
      "cf_svm_model": 0.841,
      "cg_glm_model": 0.545,
      "cg_lda_model": 0.003,
      "cg_nn_model": 0.729,
      "cg_rf_model": 0.53,
      "cg_svm_model": 0.524
    },
    "ensemble": {
      "cf": 0.5905932137783125,
      "cg": 0.46612824995879987,
      "overall": 0.534
    },
    "features": {
      "latitude": 23.75,
      "longitude": 121.25
    }
  },
  {
    "date": "2023-05-29",
    "individual_predictions": {
      "cf_glm_model": 0.534,
      "cf_lda_model": 0.998,
      "cf_nn_model": 0.443,
      "cf_nn_nn_model": 0.152,
      "cf_rf_model": 0.39,
      "cf_svm_model": 0.86,
      "cg_glm_model": 0.37,
      "cg_lda_model": 0.087,
      "cg_nn_model": 0.409,
      "cg_rf_model": 0.545,
      "cg_svm_model": 0.617
    },
    "ensemble": {
      "cf": 0.5627074419278363,
      "cg": 0.4059374587582692,
      "overall": 0.4913636363636363
    },
    "features": {
      "latitude": 24.0,
      "longitude": 121.25
    }
  },
  {
    "date": "2023-05-29",
    "individual_predictions": {
      "cf_glm_model": 0.534,
      "cf_lda_model": 0.998,
      "cf_nn_model": 0.443,
      "cf_nn_nn_model": 0.152,
      "cf_rf_model": 0.367,
      "cf_svm_model": 0.86,
      "cg_glm_model": 0.373,
      "cg_lda_model": 0.141,
      "cg_nn_model": 0.409,
      "cg_rf_model": 0.555,
      "cg_svm_model": 0.617
    },
    "ensemble": {
      "cf": 0.5588655866622101,
      "cg": 0.41909528198421525,
      "overall": 0.4953636363636363
    },
    "features": {
      "latitude": 24.25,
      "longitude": 121.25
    }
  },
  {
    "date": "2023-05-29",
    "individual_predictions": {
      "cf_glm_model": 0.534,
      "cf_lda_model": 0.998,
      "cf_nn_model": 0.443,
      "cf_nn_nn_model": 0.152,
      "cf_rf_model": 0.337,
      "cf_svm_model": 0.86,
      "cg_glm_model": 0.373,
      "cg_lda_model": 0.185,
      "cg_nn_model": 0.409,
      "cg_rf_model": 0.545,
      "cg_svm_model": 0.617
    },
    "ensemble": {
      "cf": 0.553849698398818,
      "cg": 0.42575141753502416,
      "overall": 0.4957272727272727
    },
    "features": {
      "latitude": 24.5,
      "longitude": 121.25
    }
  },
  {
    "date": "2023-05-29",
    "individual_predictions": {
      "cf_glm_model": 0.539,
      "cf_lda_model": 0.967,
      "cf_nn_model": 0.443,
      "cf_nn_nn_model": 0.152,
      "cf_rf_model": 0.933,
      "cf_svm_model": 0.865,
      "cg_glm_model": 0.319,
      "cg_lda_model": 0.982,
      "cg_nn_model": 0.414,
      "cg_rf_model": 0.673,
      "cg_svm_model": 0.644
    },
    "ensemble": {
      "cf": 0.6497113299472236,
      "cg": 0.6064629417708302,
      "overall": 0.6300909090909091
    },
    "features": {
      "latitude": 24.75,
      "longitude": 121.25
    }
  },
  {
    "date": "2023-05-29",
    "individual_predictions": {
      "cf_glm_model": 0.548,
      "cf_lda_model": 0.918,
      "cf_nn_model": 0.297,
      "cf_nn_nn_model": 0.102,
      "cf_rf_model": 0.919,
      "cf_svm_model": 0.871,
      "cg_glm_model": 0.237,
      "cg_lda_model": 0.995,
      "cg_nn_model": 0.468,
      "cg_rf_model": 0.674,
      "cg_svm_model": 0.678
    },
    "ensemble": {
      "cf": 0.6091710798688723,
      "cg": 0.6102235258245692,
      "overall": 0.6097272727272728
    },
    "features": {
      "latitude": 25.0,
      "longitude": 121.25
    }
  },
  {
    "date": "2023-05-29",
    "individual_predictions": {
      "cf_glm_model": 0.561,
      "cf_lda_model": 0.953,
      "cf_nn_model": 0.603,
      "cf_nn_nn_model": 0.283,
      "cf_rf_model": 0.82,
      "cf_svm_model": 0.876,
      "cg_glm_model": 0.141,
      "cg_lda_model": 0.991,
      "cg_nn_model": 0.508,
      "cg_rf_model": 0.67,
      "cg_svm_model": 0.718
    },
    "ensemble": {
      "cf": 0.6826771053106356,
      "cg": 0.6056583148277985,
      "overall": 0.6476363636363636
    },
    "features": {
      "latitude": 25.25,
      "longitude": 121.25
    }
  },
  {
    "date": "2023-05-29",
    "individual_predictions": {
      "cf_glm_model": 0.518,
      "cf_lda_model": 0.948,
      "cf_nn_model": 0.554,
      "cf_nn_nn_model": 0.251,
      "cf_rf_model": 0.651,
      "cf_svm_model": 0.846,
      "cg_glm_model": 0.502,
      "cg_lda_model": 0.915,
      "cg_nn_model": 0.556,
      "cg_rf_model": 0.53,
      "cg_svm_model": 0.545
    },
    "ensemble": {
      "cf": 0.62795807936869,
      "cg": 0.6097494188383136,
      "overall": 0.6196363636363637
    },
    "features": {
      "latitude": 22.0,
      "longitude": 121.5
    }
  },
  {
    "date": "2023-05-29",
    "individual_predictions": {
      "cf_glm_model": 0.52,
      "cf_lda_model": 0.956,
      "cf_nn_model": 0.554,
      "cf_nn_nn_model": 0.251,
      "cf_rf_model": 0.704,
      "cf_svm_model": 0.849,
      "cg_glm_model": 0.478,
      "cg_lda_model": 0.895,
      "cg_nn_model": 0.417,
      "cg_rf_model": 0.535,
      "cg_svm_model": 0.559
    },
    "ensemble": {
      "cf": 0.6388885931247006,
      "cg": 0.5768523357249706,
      "overall": 0.6107272727272728
    },
    "features": {
      "latitude": 22.25,
      "longitude": 121.5
    }
  },
  {
    "date": "2023-05-29",
    "individual_predictions": {
      "cf_glm_model": 0.524,
      "cf_lda_model": 0.955,
      "cf_nn_model": 0.554,
      "cf_nn_nn_model": 0.251,
      "cf_rf_model": 0.671,
      "cf_svm_model": 0.853,
      "cg_glm_model": 0.443,
      "cg_lda_model": 0.933,
      "cg_nn_model": 0.352,
      "cg_rf_model": 0.55,
      "cg_svm_model": 0.578
    },
    "ensemble": {
      "cf": 0.6344516658329911,
      "cg": 0.5712883989392187,
      "overall": 0.6058181818181819
    },
    "features": {
      "latitude": 22.5,
      "longitude": 121.5
    }
  }
]